Workbook

Sheet Factures 2025
A1: Date | B1: Client | C1: Salarié.e | D1: Numéro Facture | E1: Montant HT | F1: TVA | G1: Montant TTC | H1: Payée | I1: Jours facturés | J1: TJf | N1: Année | O1: Mois
A2: 45666 | B2: OpenClassrooms | C2: Gaetan | D2: F-2025-01-268 | E2: =I2*J2 -> 167.2 | F2: =0.2*E2 -> 33.44 | G2: =E2+F2 -> 200.64 | H2: oui | I2: 1 | J2: 167.2 | N2: =YEAR(A2) -> 2025 | O2: =MONTH(A2) -> 1
A3: 45667 | B3: GEMA | C3: Alison | D3: F-2025-01-269 | E3: =I3*J3 -> 150 | F3: 0 | G3: =E3+F3 -> 150 | H3: oui | I3: 0.5 | J3: 300 | N3: =YEAR(A3) -> 2025 | O3: =MONTH(A3) -> 1
A4: 45671 | B4: Simplon | C4: Alison | D4: F-2025-01-270 | E4: =I4*J4 -> 950 | F4: 0 | G4: =E4+F4 -> 950 | H4: oui | I4: 2 | J4: 475 | N4: =YEAR(A4) -> 2025 | O4: =MONTH(A4) -> 1
A5: 45672 | B5: Simplon | C5: Gaetan | D5: F-2025-01-271 | E5: =I5*J5 -> 950 | F5: 0 | G5: =E5+F5 -> 950 | H5: oui | I5: 2 | J5: 475 | N5: =YEAR(A5) -> 2025 | O5: =MONTH(A5) -> 1
A6: 45678 | B6: Elli Up | C6: Alison | D6: F-2025-01-272 | E6: =I6*J6 -> 650 | F6: 0 | G6: =E6+F6 -> 650 | H6: oui | I6: 1 | J6: 650 | N6: =YEAR(A6) -> 2025 | O6: =MONTH(A6) -> 1
A7: 45681 | B7: Elli Up | C7: Alison | D7: F-2025-01-273 | E7: =I7*J7 -> 1300 | F7: 0 | G7: =E7+F7 -> 1300 | H7: oui | I7: 2 | J7: 650 | N7: =YEAR(A7) -> 2025 | O7: =MONTH(A7) -> 1
A8: 45681 | B8: Elli Up | C8: Alison | D8: F-2025-01-274 | E8: =I8*J8 -> 150 | F8: 0 | G8: =E8+F8 -> 150 | H8: oui | I8: 0.5 | J8: 300 | N8: =YEAR(A8) -> 2025 | O8: =MONTH(A8) -> 1
A9: 45688 | B9: Aleysia | C9: Gaetan | D9: F-2025-01-275 | E9: =I9*J9 -> 8250 | F9: =0.2*E9 -> 1650 | G9: =E9+F9 -> 9900 | H9: oui | I9: 16.5 | J9: 500 | N9: =YEAR(A9) -> 2025 | O9: =MONTH(A9) -> 1
A10: 45693 | B10: OpenClassrooms | C10: Gaetan | D10: F-2025-02-276 | E10: =I10*J10 -> 175 | F10: =0.2*E10 -> 35 | G10: =E10+F10 -> 210 | H10: oui | I10: 1 | J10: 175 | N10: =YEAR(A10) -> 2025 | O10: =MONTH(A10) -> 2
A11: 45698 | B11: Elli Up | C11: Alison | D11: F-2025-02-277 | E11: =I11*J11 -> 150 | F11: 0 | G11: =E11+F11 -> 150 | H11: non | I11: 0.5 | J11: 300 | N11: =YEAR(A11) -> 2025 | O11: =MONTH(A11) -> 2
A12: 45702 | B12: Simplon | C12: Gaetan | D12: F-2025-02-278 | E12: =I12*J12 -> 475 | F12: 0 | G12: =E12+F12 -> 475 | H12: non | I12: 1 | J12: 475 | N12: =YEAR(A12) -> 2025 | O12: =MONTH(A12) -> 2
A13: 45705 | B13: Simplon | C13: Alison | D13: F-2025-02-279 | E13: =I13*J13 -> 950 | F13: 0 | G13: =E13+F13 -> 950 | H13: non | I13: 2 | J13: 475 | N13: =YEAR(A13) -> 2025 | O13: =MONTH(A13) -> 2
A14: 45737 | B14: Elli Up | C14: Alison | D14: F-2025-03-294 | E14: 250 | F14: 0 | G14: 250 | H14: non | I14: 0 | J14: 0 | N14: =YEAR(A14) -> 2025 | O14: =MONTH(A14) -> 3
A15: 45713 | B15: WM | C15: Alison | D15: F-2025-02-281 | E15: =I15*J15 -> 450 | F15: 0 | G15: =E15+F15 -> 450 | H15: non | I15: 0.5 | J15: 900 | N15: =YEAR(A15) -> 2025 | O15: =MONTH(A15) -> 2
A16: 45713 | B16: Elli Up | C16: Alison | D16: F-2025-02-282 | E16: =I16*J16 -> 350 | F16: 0 | G16: =E16+F16 -> 350 | H16: non | I16: 0.5 | J16: 700 | N16: =YEAR(A16) -> 2025 | O16: =MONTH(A16) -> 2
A17: 45714 | B17: Entropics | C17: Alison | D17: F-2025-02-283 | E17: =I17*J17 -> 4000 | F17: =0.2*E17 -> 800 | G17: =E17+F17 -> 4800 | H17: oui | I17: 8 | J17: 500 | N17: =YEAR(A17) -> 2025 | O17: =MONTH(A17) -> 2
A18: 45714 | B18: GL events | C18: Gaetan | D18: F-2025-02-284 | E18: =I18*J18 -> 1350 | F18: =0.2*E18 -> 270 | G18: =E18+F18 -> 1620 | H18: non | I18: 3 | J18: 450 | N18: =YEAR(A18) -> 2025 | O18: =MONTH(A18) -> 2
A19: 45716 | B19: Aleysia | C19: Gaetan | D19: F-2025-02-285 | E19: =I19*J19 -> 7250 | F19: =0.2*E19 -> 1450 | G19: =E19+F19 -> 8700 | H19: non | I19: 14.5 | J19: 500 | N19: =YEAR(A19) -> 2025 | O19: =MONTH(A19) -> 2
A20: 45720 | B20: OpenClassrooms | C20: Gaetan | D20: F-2025-03-286 | E20: =I20*J20 -> 175 | F20: =0.2*E20 -> 35 | G20: =E20+F20 -> 210 | H20: non | I20: 1 | J20: 175 | N20: =YEAR(A20) -> 2025 | O20: =MONTH(A20) -> 3
A21: 45723 | B21: GEMA | C21: Alison | D21: F-2025-03-287 | E21: =I21*J21 -> 300 | F21: 0 | G21: =E21+F21 -> 300 | H21: non | I21: 0.5 | J21: 600 | N21: =YEAR(A21) -> 2025 | O21: =MONTH(A21) -> 3
A22: 45727 | B22: Simplon | C22: Gaetan | D22: F-2025-03-288 | E22: =I22*J22 -> 950 | F22: =0.2*E22 -> 190 | G22: =E22+F22 -> 1140 | H22: non | I22: 2 | J22: 475 | N22: =YEAR(A22) -> 2025 | O22: =MONTH(A22) -> 3
A23: 45734 | B23: Sparks | C23: Alison | D23: F-2025-03-289 | E23: =I23*J23 -> 750 | F23: 0 | G23: =E23+F23 -> 750 | H23: non | I23: 1 | J23: 750 | N23: =YEAR(A23) -> 2025 | O23: =MONTH(A23) -> 3
A24: 45734 | B24: Simplon | C24: Alison | D24: F-2025-03-290 | E24: =I24*J24 -> 2375 | F24: 0 | G24: =E24+F24 -> 2375 | H24: non | I24: 5 | J24: 475 | N24: =YEAR(A24) -> 2025 | O24: =MONTH(A24) -> 3
A25: 45734 | B25: Elli Up | C25: Alison | D25: F-2025-03-293 | E25: 400 | F25: 0 | G25: =E25+F25 -> 400 | H25: non | I25: 1 | J25: =800-150 -> 650 | N25: =YEAR(A25) -> 2025 | O25: =MONTH(A25) -> 3
A26: 45744 | B26: Sparks | C26: Alison | D26: F-2025-03-295 | E26: =I26*J26 -> 750 | F26: 0 | G26: =E26+F26 -> 750 | H26: non | I26: 1 | J26: 750 | N26: =YEAR(A26) -> 2025 | O26: =MONTH(A26) -> 3
A27: 45746 | B27: Albert School | C27: Alison | E27: =I27*J27 -> 1890 | F27: 0 | G27: =E27+F27 -> 1890 | H27: prev | I27: 2 | J27: 945 | N27: =YEAR(A27) -> 2025 | O27: =MONTH(A27) -> 3
A28: 45746 | B28: Aleysia | C28: Gaetan | E28: =I28*J28 -> 7000 | F28: =0.2*E28 -> 1400 | G28: =E28+F28 -> 8400 | H28: prev | I28: 14 | J28: 500 | N28: =YEAR(A28) -> 2025 | O28: =MONTH(A28) -> 3
A29: 45746 | B29: Sparks | C29: Alison | E29: =I29*J29 -> 900 | F29: 0 | G29: =E29+F29 -> 900 | H29: prev | I29: 1 | J29: 900 | N29: =YEAR(A29) -> 2025 | O29: =MONTH(A29) -> 3
A30: 45746 | B30: WM | C30: Alison | E30: =I30*J30 -> 450 | F30: 0 | G30: =E30+F30 -> 450 | H30: prev | I30: 0.5 | J30: 900 | N30: =YEAR(A30) -> 2025 | O30: =MONTH(A30) -> 3
A31: 45746 | B31: Simplon | C31: Alison | E31: =2100 -> 2100 | F31: 0 | G31: =E31+F31 -> 2100 | H31: prosp | I31: 0 | J31: 0 | N31: =YEAR(A31) -> 2025 | O31: =MONTH(A31) -> 3
A32: 45746 | B32: Sparks | C32: Alison | E32: =I32*J32 -> 750 | F32: =0.2*E32 -> 150 | G32: =E32+F32 -> 900 | H32: prev | I32: 1 | J32: 750 | N32: =YEAR(A32) -> 2025 | O32: =MONTH(A32) -> 3
A33: 45775 | B33: Entropics | C33: Gaetan | E33: =I33*J33 -> 2000 | F33: =0.2*E33 -> 400 | G33: =E33+F33 -> 2400 | H33: prev | I33: 4 | J33: 500 | N33: =YEAR(A33) -> 2025 | O33: =MONTH(A33) -> 4
A34: 45777 | B34: Plouf SOGEV | C34: Gaetan | E34: =I34*J34 -> 10000 | F34: =0.2*E34 -> 2000 | G34: =E34+F34 -> 12000 | H34: prosp | I34: 20 | J34: 500 | N34: =YEAR(A34) -> 2025 | O34: =MONTH(A34) -> 4
A35: 45777 | B35: Plouf Altea | C35: Gaetan | E35: =I35*J35 -> 5000 | F35: =0.2*E35 -> 1000 | G35: =E35+F35 -> 6000 | H35: prosp | I35: 1 | J35: 5000 | N35: =YEAR(A35) -> 2025 | O35: =MONTH(A35) -> 4
A36: 45777 | B36: Albert School | C36: Alison | E36: =I36*J36 -> 810 | F36: =0.2*E36 -> 162 | G36: =E36+F36 -> 972 | H36: prev | I36: 1 | J36: 810 | N36: =YEAR(A36) -> 2025 | O36: =MONTH(A36) -> 4
A37: 45777 | B37: Aleysia | C37: Gaetan | E37: =I37*J37 -> 8000 | F37: =0.2*E37 -> 1600 | G37: =E37+F37 -> 9600 | H37: prev | I37: 16 | J37: 500 | N37: =YEAR(A37) -> 2025 | O37: =MONTH(A37) -> 4
A38: 45777 | B38: Plouf ALBEDO | C38: Gaetan | E38: =I38*J38 -> 5000 | F38: =0.2*E38 -> 1000 | G38: =E38+F38 -> 6000 | H38: prosp | I38: 10 | J38: 500 | N38: =YEAR(A38) -> 2025 | O38: =MONTH(A38) -> 4
A39: 45777 | B39: Simplon | C39: Gaetan | E39: =I39*J39 -> 950 | F39: 0 | G39: =E39+F39 -> 950 | H39: prev | I39: 2 | J39: 475 | N39: =YEAR(A39) -> 2025 | O39: =MONTH(A39) -> 4
A40: 45777 | B40: Plouf INGEO | C40: Gaetan | E40: =I40*J40 -> 5000 | F40: =0.2*E40 -> 1000 | G40: =E40+F40 -> 6000 | H40: prev | I40: 10 | J40: 500 | N40: =YEAR(A40) -> 2025 | O40: =MONTH(A40) -> 4
A41: 45800 | B41: Sparks | C41: Alison | E41: 900 | F41: 0 | G41: 900 | H41: prosp | I41: 0 | J41: 0 | N41: =YEAR(A41) -> 2025 | O41: =MONTH(A41) -> 5
A42: 45805 | B42: Entropics | C42: Alison | E42: =I42*J42 -> 6000 | F42: =0.2*E42 -> 1200 | G42: =E42+F42 -> 7200 | H42: prosp | I42: 12 | J42: 500 | N42: =YEAR(A42) -> 2025 | O42: =MONTH(A42) -> 5
A43: 45807 | B43: Albert School | C43: Alison | E43: =I43*J43 -> 1350 | F43: =0.2*E43 -> 270 | G43: =E43+F43 -> 1620 | H43: prev | I43: 2 | J43: 675 | N43: =YEAR(A43) -> 2025 | O43: =MONTH(A43) -> 5
A44: 45807 | B44: Aleysia | C44: Gaetan | E44: =I44*J44 -> 6000 | F44: =0.2*E44 -> 1200 | G44: =E44+F44 -> 7200 | H44: prev | I44: 12 | J44: 500 | N44: =YEAR(A44) -> 2025 | O44: =MONTH(A44) -> 5
A45: 45807 | B45: Simplon | C45: Gaetan | E45: =I45*J45 -> 950 | F45: =0.2*E45 -> 190 | G45: =E45+F45 -> 1140 | H45: prev | I45: 2 | J45: 475 | N45: =YEAR(A45) -> 2025 | O45: =MONTH(A45) -> 5
A46: 45808 | B46: Plouf Réunion | C46: Gaetan | E46: =I46*J46 -> 630 | F46: =0.2*E46 -> 126 | G46: =E46+F46 -> 756 | H46: prosp | I46: 6 | J46: 105 | N46: =YEAR(A46) -> 2025 | O46: =MONTH(A46) -> 5
A47: 45808 | B47: Optim Ressources | C47: Alison | E47: =I47*J47 -> 2700 | F47: =0.2*E47 -> 540 | G47: =E47+F47 -> 3240 | H47: prosp | I47: 3 | J47: 900 | N47: =YEAR(A47) -> 2025 | O47: =MONTH(A47) -> 5
A48: 45831 | B48: Sparks | C48: Alison | E48: 900 | F48: 0 | G48: 900 | H48: prosp | I48: 0 | J48: 0 | N48: =YEAR(A48) -> 2025 | O48: =MONTH(A48) -> 6
A49: 45838 | B49: Plouf H8 | C49: Gaetan | E49: =I49*J49 -> 10000 | F49: =0.2*E49 -> 2000 | G49: =E49+F49 -> 12000 | H49: prev | I49: 20 | J49: 500 | N49: =YEAR(A49) -> 2025 | O49: =MONTH(A49) -> 6
A50: 45838 | B50: Aleysia | C50: Gaetan | E50: =I50*J50 -> 8000 | F50: =0.2*E50 -> 1600 | G50: =E50+F50 -> 9600 | H50: prev | I50: 16 | J50: 500 | N50: =YEAR(A50) -> 2025 | O50: =MONTH(A50) -> 6
A51: 45838 | B51: Simplon | C51: Gaetan | E51: =I51*J51 -> 950 | F51: =0.2*E51 -> 190 | G51: =E51+F51 -> 1140 | H51: prev | I51: 2 | J51: 475 | N51: =YEAR(A51) -> 2025 | O51: =MONTH(A51) -> 6
A52: 45838 | B52: Sparks - AI900 | C52: Alison | E52: =I52*J52 -> 1800 | F52: 0 | G52: =E52+F52 -> 1800 | H52: prosp | I52: 2 | J52: 900 | N52: =YEAR(A52) -> 2025 | O52: =MONTH(A52) -> 6
A53: 45838 | B53: Sparks - schneider | C53: Alison | E53: =I53*J53 -> 4000 | F53: 0 | G53: =E53+F53 -> 4000 | H53: prosp | I53: 5 | J53: 800 | N53: =YEAR(A53) -> 2025 | O53: =MONTH(A53) -> 6
A54: 45838 | B54: GL events | C54: Nicolas | E54: =I54*J54 -> 9720 | F54: =0.2*E54 -> 1944 | G54: =E54+F54 -> 11664 | H54: prev | I54: 18 | J54: 540 | N54: =YEAR(A54) -> 2025 | O54: =MONTH(A54) -> 6
A55: 45868 | B55: Aleysia | C55: Gaetan | E55: =I55*J55 -> 9500 | F55: =0.2*E55 -> 1900 | G55: =E55+F55 -> 11400 | H55: prev | I55: 19 | J55: 500 | N55: =YEAR(A55) -> 2025 | O55: =MONTH(A55) -> 7
A56: 45868 | B56: GL events | C56: Nicolas | E56: =I56*J56 -> 9720 | F56: =0.2*E56 -> 1944 | G56: =E56+F56 -> 11664 | H56: prev | I56: 18 | J56: 540 | N56: =YEAR(A56) -> 2025 | O56: =MONTH(A56) -> 7
A57: 45898 | B57: GL events | C57: Nicolas | E57: =I57*J57 -> 2700 | F57: =0.2*E57 -> 540 | G57: =E57+F57 -> 3240 | H57: prev | I57: 5 | J57: 540 | N57: =YEAR(A57) -> 2025 | O57: =MONTH(A57) -> 8
A58: 45899 | B58: Aleysia | C58: Gaetan | E58: =I58*J58 -> 2500 | F58: =0.2*E58 -> 500 | G58: =E58+F58 -> 3000 | H58: prev | I58: 5 | J58: 500 | N58: =YEAR(A58) -> 2025 | O58: =MONTH(A58) -> 8
A59: 45928 | B59: GL events | C59: Nicolas | E59: =I59*J59 -> 9720 | F59: =0.2*E59 -> 1944 | G59: =E59+F59 -> 11664 | H59: prev | I59: 18 | J59: 540 | N59: =YEAR(A59) -> 2025 | O59: =MONTH(A59) -> 9
A60: 45930 | B60: Mission Gaetan | C60: Gaetan | E60: =I60*J60 -> 7700 | F60: =0.2*E60 -> 1540 | G60: =E60+F60 -> 9240 | H60: prosp | I60: 14 | J60: 550 | N60: =YEAR(A60) -> 2025 | O60: =MONTH(A60) -> 9
A61: 45930 | B61: Simplon | C61: Gaetan | E61: =I61*J61 -> 1425 | F61: =0.2*E61 -> 285 | G61: =E61+F61 -> 1710 | H61: prev | I61: 3 | J61: 475 | N61: =YEAR(A61) -> 2025 | O61: =MONTH(A61) -> 9
A62: 45958 | B62: GL events | C62: Nicolas | E62: =I62*J62 -> 9720 | F62: =0.2*E62 -> 1944 | G62: =E62+F62 -> 11664 | H62: prev | I62: 18 | J62: 540 | N62: =YEAR(A62) -> 2025 | O62: =MONTH(A62) -> 10
A63: 45960 | B63: Mission Gaetan | C63: Gaetan | E63: =I63*J63 -> 7700 | F63: =0.2*E63 -> 1540 | G63: =E63+F63 -> 9240 | H63: prosp | I63: 14 | J63: 550 | N63: =YEAR(A63) -> 2025 | O63: =MONTH(A63) -> 10
A64: 45988 | B64: Mission Nicolas | C64: Nicolas | E64: =I64*J64 -> 9720 | F64: =0.2*E64 -> 1944 | G64: =E64+F64 -> 11664 | H64: prev | I64: 18 | J64: 540 | N64: =YEAR(A64) -> 2025 | O64: =MONTH(A64) -> 11
A65: 45991 | B65: Mission Gaetan | C65: Gaetan | E65: =I65*J65 -> 7700 | F65: =0.2*E65 -> 1540 | G65: =E65+F65 -> 9240 | H65: prosp | I65: 14 | J65: 550 | N65: =YEAR(A65) -> 2025 | O65: =MONTH(A65) -> 11
... A68: 46021 | B68: Mission Gaetan | C68: Gaetan | E68: =I68*J68 -> 7700 | F68: =0.2*E68 -> 1540 | G68: =E68+F68 -> 9240 | H68: prosp | I68: 14 | J68: 550 | N68: =YEAR(A68) -> 2025 | O68: =MONTH(A68) -> 12
I69: 0 | J69: 0 | N69: =YEAR(A69) -> 1900 | O69: =MONTH(A69) -> 1
I70: 0 | J70: 0 | N70: =YEAR(A70) -> 1900 | O70: =MONTH(A70) -> 1
I71: 0 | J71: 0 | N71: =YEAR(A71) -> 1900 | O71: =MONTH(A71) -> 1
I72: 0 | J72: 0 | N72: =YEAR(A72) -> 1900 | O72: =MONTH(A72) -> 1
I73: 0 | J73: 0 | N73: =YEAR(A73) -> 1900 | O73: =MONTH(A73) -> 1
I74: 0 | J74: 0 | N74: =YEAR(A74) -> 1900 | O74: =MONTH(A74) -> 1
I75: 0 | J75: 0 | N75: =YEAR(A75) -> 1900 | O75: =MONTH(A75) -> 1
I76: 0 | J76: 0 | N76: =YEAR(A76) -> 1900 | O76: =MONTH(A76) -> 1
I77: 0 | J77: 0 | N77: =YEAR(A77) -> 1900 | O77: =MONTH(A77) -> 1
I78: 0 | J78: 0 | N78: =YEAR(A78) -> 1900 | O78: =MONTH(A78) -> 1
I79: 0 | J79: 0 | N79: =YEAR(A79) -> 1900 | O79: =MONTH(A79) -> 1
I80: 0 | J80: 0 | N80: =YEAR(A80) -> 1900 | O80: =MONTH(A80) -> 1
... I83: 0 | J83: 0 | N83: =YEAR(A83) -> 1900 | O83: =MONTH(A83) -> 1
N84: =YEAR(A84) -> 1900 | O84: =MONTH(A84) -> 1
N85: =YEAR(A85) -> 1900 | O85: =MONTH(A85) -> 1
N86: =YEAR(A86) -> 1900 | O86: =MONTH(A86) -> 1
N87: =YEAR(A87) -> 1900 | O87: =MONTH(A87) -> 1
N88: =YEAR(A88) -> 1900 | O88: =MONTH(A88) -> 1
N89: =YEAR(A89) -> 1900 | O89: =MONTH(A89) -> 1
N90: =YEAR(A90) -> 1900 | O90: =MONTH(A90) -> 1
N91: =YEAR(A91) -> 1900 | O91: =MONTH(A91) -> 1
N92: =YEAR(A92) -> 1900 | O92: =MONTH(A92) -> 1
N93: =YEAR(A93) -> 1900 | O93: =MONTH(A93) -> 1
N94: =YEAR(A94) -> 1900 | O94: =MONTH(A94) -> 1
N95: =YEAR(A95) -> 1900 | O95: =MONTH(A95) -> 1
... N113: =YEAR(A113) -> 1900 | O113: =MONTH(A113) -> 1

Sheet Bilan 2025
C2: Réel | D2: Prev | E2: Prospection | M2: 2024 réel | N2: 2025 estim | O2: 2026 estim
B3: Total Recettes | C3: =SUM(C4:C5) -> 33667.2 | D3: =SUM(D4:D5) -> 164062.2 | E3: =SUM(E4:E5) -> 233892.2 | H3: Salaires | I3: Primes | L3: Charges générales | M3: =35000-M6-M5 -> 18100 | N3: 15500 | O3: 16000
B4: CA 2024 | C4: =SUMIFS('Factures 2025'!E:E,'Factures 2025'!H:H,"oui",'Factures 2025'!N:N,"<2026")+SUMIFS('Factures 2025'!E:E,'Factures 2025'!H:H,"non",'Factures 2025'!N:N,"<2026") -> 33667.2 | D4: =C4+SUMIFS('Factures 2025'!E:E,'Factures 2025'!H:H,"prev",'Factures 2025'!N:N,"<2026") -> 164062.2 | E4: =D4+SUMIFS('Factures 2025'!E:E,'Factures 2025'!H:H,"prosp",'Factures 2025'!N:N,"<2026") -> 233892.2 | G4: Alison | H4: 4000 | L4: Loyers SCI | N4: =1750*7 -> 12250 | O4: =1750*12 -> 21000
B5: Divers | C5: 0 | D5: 0 | E5: 0 | G5: Gaëtan | H5: 4000 | L5: Prestation | M5: 3400 | N5: 6000
G6: JS | H6: 500 | I6: 1000 | L6: Sous-traitance | M6: 13500 | N6: =350*3+5000+1500 -> 7550
B7: Facturé non payé | C7: =SUMIFS('Factures 2025'!E:E,'Factures 2025'!H:H,"non",'Factures 2025'!N:N,"<2026") -> 16925 | D7: HT | G7: Nicolas | H7: 4750 | L7: WiiSmile | M7: 6300 | N7: =300*12+100*7+700+29*3*12+29*7 -> 6247 | O7: =400*12+700+29*4*12 -> 6892
C8: =SUMIFS('Factures 2025'!G:G,'Factures 2025'!H:H,"non",'Factures 2025'!N:N,"<2026") -> 18870 | D8: TTC | L8: Salaires | M8: =118000-M11 -> 114500 | O8: =(H4+H5+H7)*12+I6*12 -> 165000
L9: Cotisations sociales | M9: =52000-M7 -> 45700 | O9: =(H4+H5+H7)*12*0.42 -> 64260
C10: Réel | D10: Prev | E10: Prospection | L10: Taxe d'apprentissage | M10: 1200 | N10: 1200 | O10: 1500
B11: Total Dépenses | C11: =SUM(C12:C13) -> 244426 | D11: =SUM(D12:D13) -> 244426 | E11: =SUM(E12:E13) -> 244426 | L11: TR | M11: 3500 | N11: =6*18*(12*3+7) -> 4644 | O11: =6*18*(12*4) -> 5184
B12: Charges globales | C12: =N13 -> 53391 | D12: =C12 -> 53391 | E12: =D12 -> 53391
B13: Salaires | C13: =1.42*((H4+H5)*12+H7*7)+H6*9+(I4+I5+I7)*1.42+3*I6 -> 191035 | D13: =C13 -> 191035 | E13: =D13 -> 191035 | L13: Total dépenses | M13: =SUM(M3:M12) -> 206200 | N13: =SUM(N3:N12) -> 53391 | O13: =SUM(O3:O12) -> 279836
C16: Réel | D16: Prev | E16: Prospection
B17: Balance | C17: =C3-C11 -> -210758.8 | D17: =D3-D11 -> -80363.8 | E17: =E3-E11 -> -10533.8
C20: Réel | D20: Prev | E20: Prospection
B21: Total Recettes | C21: =SUM(C22:C24) -> 33667.2 | D21: =SUM(D22:D24) -> 164062.2 | E21: =SUM(E22:E24) -> 233892.2
B22: CA Alison | C22: =SUMIFS('Factures 2025'!E:E,'Factures 2025'!H:H,"oui",'Factures 2025'!N:N,"<2026",'Factures 2025'!C:C,"Alison")+SUMIFS('Factures 2025'!E:E,'Factures 2025'!H:H,"non",'Factures 2025'!N:N,"<2026",'Factures 2025'!C:C,"Alison") -> 13925 | D22: =C22+SUMIFS('Factures 2025'!E:E,'Factures 2025'!H:H,"prev",'Factures 2025'!N:N,"<2026",'Factures 2025'!C:C,"Alison") -> 20075 | E22: =D22+SUMIFS('Factures 2025'!E:E,'Factures 2025'!H:H,"prosp",'Factures 2025'!N:N,"<2026",'Factures 2025'!C:C,"Alison") -> 38475
B23: CA Gaëtan | C23: =SUMIFS('Factures 2025'!E:E,'Factures 2025'!H:H,"oui",'Factures 2025'!N:N,"<2026",'Factures 2025'!C:C,"Gaetan")+SUMIFS('Factures 2025'!E:E,'Factures 2025'!H:H,"non",'Factures 2025'!N:N,"<2026",'Factures 2025'!C:C,"Gaetan") -> 19742.2 | D23: =C23+SUMIFS('Factures 2025'!E:E,'Factures 2025'!H:H,"prev",'Factures 2025'!N:N,"<2026",'Factures 2025'!C:C,"Gaetan") -> 82967.2 | E23: =D23+SUMIFS('Factures 2025'!E:E,'Factures 2025'!H:H,"prosp",'Factures 2025'!N:N,"<2026",'Factures 2025'!C:C,"Gaetan") -> 134397.2
B24: CA Nicolas | C24: =SUMIFS('Factures 2025'!E:E,'Factures 2025'!H:H,"oui",'Factures 2025'!N:N,"<2026",'Factures 2025'!C:C,"Nicolas")+SUMIFS('Factures 2025'!E:E,'Factures 2025'!H:H,"non",'Factures 2025'!N:N,"<2026",'Factures 2025'!C:C,"Nicolas") -> 0 | D24: =C24+SUMIFS('Factures 2025'!E:E,'Factures 2025'!H:H,"prev",'Factures 2025'!N:N,"<2026",'Factures 2025'!C:C,"Nicolas") -> 61020 | E24: =D24+SUMIFS('Factures 2025'!E:E,'Factures 2025'!H:H,"prosp",'Factures 2025'!N:N,"<2026",'Factures 2025'!C:C,"Nicolas") -> 61020

Sheet Factures 2024
A1: Date | B1: Client | C1: Salarié.e | D1: Numéro Facture | E1: Montant HT | F1: TVA | G1: Montant TTC | H1: Payée | I1: Jours facturés | J1: TJf | K1: Jours réel | L1: TJ réel | M1: Vide | N1: Année | O1: Mois
A2: 45296 | B2: OpenClassrooms | C2: Gaetan | D2: 2024-01-05-000151 | E2: =I2*J2 -> 660 | F2: =0.2*E2 -> 132 | G2: =F2+E2 -> 792 | H2: oui | I2: 1 | J2: 660 | K2: 1 | L2: =E2/K2 -> 660 | N2: =YEAR(A2) -> 2024 | O2: =MONTH(A2) -> 1
A3: 45296 | B3: OpenClassrooms | C3: Alison | D3: 2024-01-06-000152 | E3: =I3*J3 -> 1180 | F3: =0.2*E3 -> 236 | G3: =F3+E3 -> 1416 | H3: oui | I3: 2 | J3: 590 | K3: 2 | L3: =E3/K3 -> 590 | N3: =YEAR(A3) -> 2024 | O3: =MONTH(A3) -> 1
A4: 45314 | B4: EPSI | C4: Gaetan | D4: 2024-01-23-000157 | E4: =I4*J4 -> 2296 | F4: 0 | G4: =F4+E4 -> 2296 | H4: oui | I4: 4 | J4: =7*82 -> 574 | K4: 2 | L4: =E4/K4 -> 1148 | N4: =YEAR(A4) -> 2024 | O4: =MONTH(A4) -> 1
A5: 45314 | B5: OpenClassrooms | C5: Alison | D5: 2024-01-23-000158 | E5: =I5*J5 -> 930 | F5: =0.2*E5 -> 186 | G5: =F5+E5 -> 1116 | H5: oui | I5: 1 | J5: 930 | K5: 0 | L5: =E5/K5 -> #DIV/0! | N5: =YEAR(A5) -> 2024 | O5: =MONTH(A5) -> 1
A6: 45321 | B6: Simplon | C6: Alison | D6: 2024-01-25-000159 | E6: =5*450+2*475+3*60 -> 3380 | F6: 0 | G6: =F6+E6 -> 3380 | H6: oui | I6: 7 | J6: 450 | L6: =E6/K6 -> #DIV/0! | N6: =YEAR(A6) -> 2024 | O6: =MONTH(A6) -> 1
A7: 45321 | B7: GCD | C7: Alison | D7: 2024-01-26-000160 | E7: =I7*J7 -> 9750 | F7: 0 | G7: =F7+E7 -> 9750 | H7: oui | I7: 15 | J7: 650 | L7: =E7/K7 -> #DIV/0! | N7: =YEAR(A7) -> 2024 | O7: =MONTH(A7) -> 1
A8: 45321 | B8: Vicinity | C8: Alison | D8: 2024-01-30-000161 | E8: =I8*J8 -> 900 | F8: =0.2*E8 -> 180 | G8: =F8+E8 -> 1080 | H8: oui | I8: 1.5 | J8: 600 | K8: 1.5 | L8: =E8/K8 -> 600 | N8: =YEAR(A8) -> 2024 | O8: =MONTH(A8) -> 1
A9: 45322 | B9: Aleysia | C9: Gaetan | D9: 2024-01-31-000162 | E9: =I9*J9 -> 7500 | F9: =0.2*E9 -> 1500 | G9: =F9+E9 -> 9000 | H9: oui | I9: 15 | J9: 500 | K9: 13 | L9: =E9/K9 -> 576.92308 | N9: =YEAR(A9) -> 2024 | O9: =MONTH(A9) -> 1
A10: 45327 | B10: OpenClassrooms | C10: Alison | D10: 2024-02-05-000163 | E10: =I10*J10 -> 840 | F10: =0.2*E10 -> 168 | G10: =F10+E10 -> 1008 | H10: oui | I10: 1 | J10: 840 | L10: =E10/K10 -> #DIV/0! | N10: =YEAR(A10) -> 2024 | O10: =MONTH(A10) -> 2
A11: 45327 | B11: OpenClassrooms | C11: Gaetan | D11: 2024-02-05-000164 | E11: =I11*J11 -> 790 | F11: =0.2*E11 -> 158 | G11: =F11+E11 -> 948 | H11: oui | I11: 1 | J11: 790 | K11: 1 | L11: =E11/K11 -> 790 | N11: =YEAR(A11) -> 2024 | O11: =MONTH(A11) -> 2
A12: 45345 | B12: EPSI | C12: Gaetan | D12: 2024-02-23-000165 | E12: =I12*J12 -> 1148 | F12: 0 | G12: =F12+E12 -> 1148 | H12: oui | I12: 2 | J12: =7*82 -> 574 | L12: =E12/K12 -> #DIV/0! | N12: =YEAR(A12) -> 2024 | O12: =MONTH(A12) -> 2
A13: 45348 | B13: Simplon | C13: Alison | D13: 2024-02-26-000166 | E13: 2000 | F13: 0 | G13: =F13+E13 -> 2000 | H13: oui | I13: 1 | J13: 2000 | K13: 1 | L13: =E13/K13 -> 2000 | N13: =YEAR(A13) -> 2024 | O13: =MONTH(A13) -> 2
A14: 45348 | B14: GCD | C14: Alison | D14: 2024-02-26-000167 | E14: =I14*J14 -> 3900 | F14: 0 | G14: =F14+E14 -> 3900 | H14: oui | I14: 6 | J14: 650 | L14: =E14/K14 -> #DIV/0! | N14: =YEAR(A14) -> 2024 | O14: =MONTH(A14) -> 2
A15: 45348 | B15: OpenClassrooms | C15: Alison | D15: 2024-02-26-000168 | E15: 855 | F15: =0.2*E15 -> 171 | G15: =F15+E15 -> 1026 | H15: oui | I15: 2 | J15: 750 | L15: =E15/K15 -> #DIV/0! | N15: =YEAR(A15) -> 2024 | O15: =MONTH(A15) -> 2
A16: 45350 | B16: Vicinity | C16: Alison | D16: 2024-02-27-000169 | E16: =I16*J16 -> 600 | F16: =0.2*E16 -> 120 | G16: =F16+E16 -> 720 | H16: oui | I16: 1 | J16: 600 | L16: =E16/K16 -> #DIV/0! | N16: =YEAR(A16) -> 2024 | O16: =MONTH(A16) -> 2
A17: 45350 | B17: Simplon | C17: Alison | D17: 2024-02-28-000170 | E17: 3650 | F17: 0 | G17: =F17+E17 -> 3650 | H17: oui | I17: 7 | J17: 475 | K17: 7 | L17: =E17/K17 -> 521.42857 | N17: =YEAR(A17) -> 2024 | O17: =MONTH(A17) -> 2
A18: 45351 | B18: Aleysia | C18: Gaetan | D18: 2024-02-29-000171 | E18: =I18*J18 -> 7500 | F18: =0.2*E18 -> 1500 | G18: =F18+E18 -> 9000 | H18: oui | I18: 15 | J18: 500 | K18: 13 | L18: =E18/K18 -> 576.92308 | N18: =YEAR(A18) -> 2024 | O18: =MONTH(A18) -> 2
A19: 45356 | B19: OpenClassrooms | C19: Alison | D19: 2024-03-05-000172 | E19: =I19*J19 -> 880 | F19: =0.2*E19 -> 176 | G19: =F19+E19 -> 1056 | H19: oui | I19: 1 | J19: 880 | L19: =E19/K19 -> #DIV/0! | N19: =YEAR(A19) -> 2024 | O19: =MONTH(A19) -> 3
A20: 45356 | B20: OpenClassrooms | C20: Gaetan | D20: 2024-03-05-000173 | E20: =I20*J20 -> 880 | F20: =0.2*E20 -> 176 | G20: =F20+E20 -> 1056 | H20: oui | I20: 1 | J20: 880 | L20: =E20/K20 -> #DIV/0! | N20: =YEAR(A20) -> 2024 | O20: =MONTH(A20) -> 3
A21: 45359 | B21: OpenClassrooms | C21: Alison | D21: 2024-03-08-000174 | E21: =I21*J21 -> 1000 | F21: =0.2*E21 -> 200 | G21: =F21+E21 -> 1200 | H21: oui | I21: 1 | J21: 1000 | L21: =E21/K21 -> #DIV/0! | N21: =YEAR(A21) -> 2024 | O21: =MONTH(A21) -> 3
A22: 45359 | B22: Simplon | C22: Gaetan | D22: 2024-03-08-000175 | E22: =I22*J22 -> 475 | F22: 0 | G22: =F22+E22 -> 475 | H22: oui | I22: 1 | J22: 475 | L22: =E22/K22 -> #DIV/0! | N22: =YEAR(A22) -> 2024 | O22: =MONTH(A22) -> 3
A23: 45364 | B23: Sparks | C23: Alison | D23: 2024-03-13-000176 | E23: =I23*J23 -> 750 | F23: 0 | G23: =F23+E23 -> 750 | H23: oui | I23: 1 | J23: 750 | L23: =E23/K23 -> #DIV/0! | N23: =YEAR(A23) -> 2024 | O23: =MONTH(A23) -> 3
A24: 45364 | B24: Vicinity | C24: Alison | D24: 2024-03-13-000177 | E24: 300 | F24: =0.2*E24 -> 60 | G24: =F24+E24 -> 360 | H24: oui | I24: 1 | J24: 600 | K24: 0.5 | L24: =E24/K24 -> 600 | N24: =YEAR(A24) -> 2024 | O24: =MONTH(A24) -> 3
A25: 45378 | B25: OpenClassrooms | C25: Alison | D25: 2024-03-22-000178 | E25: 1065 | F25: =0.2*E25 -> 213 | G25: =F25+E25 -> 1278 | H25: oui | I25: 1 | J25: =E25 -> 1065 | L25: =E25/K25 -> #DIV/0! | N25: =YEAR(A25) -> 2024 | O25: =MONTH(A25) -> 3
A26: 45380 | B26: GCD | C26: Alison | D26: 2024-03-29-000179 | E26: =I26*J26 -> 650 | F26: 0 | G26: =F26+E26 -> 650 | H26: oui | I26: 1 | J26: 650 | L26: =E26/K26 -> #DIV/0! | N26: =YEAR(A26) -> 2024 | O26: =MONTH(A26) -> 3
A27: 45380 | B27: Aleysia | C27: Gaetan | D27: 2024-03-29-000180 | E27: =I27*J27 -> 7000 | F27: =0.2*E27 -> 1400 | G27: =F27+E27 -> 8400 | H27: oui | I27: 14 | J27: 500 | K27: 12 | L27: =E27/K27 -> 583.33333 | N27: =YEAR(A27) -> 2024 | O27: =MONTH(A27) -> 3
A28: 45381 | B28: Simplon | C28: Alison | D28: 2024-03-29-000181 | E28: =4*450+7.5*475+3*60 -> 5542.5 | F28: 0 | G28: =F28+E28 -> 5542.5 | H28: oui | I28: 8 | J28: =E28/8 -> 692.8125 | L28: =E28/K28 -> #DIV/0! | N28: =YEAR(A28) -> 2024 | O28: =MONTH(A28) -> 3
A29: 45387.667 | B29: OpenClassrooms | C29: Alison | D29: 2024-04-06-000190 | E29: 598.4 | F29: =0.2*E29 -> 119.68 | G29: =F29+E29 -> 718.08 | H29: oui | I29: 1 | J29: 598.4 | L29: =E29/K29 -> #DIV/0! | N29: =YEAR(A29) -> 2024 | O29: =MONTH(A29) -> 4
A30: 45389 | B30: OpenClassrooms | C30: Gaetan | D30: 2024-04-08-000191 | E30: =I30*J30 -> 596 | F30: =0.2*E30 -> 119.2 | G30: =F30+E30 -> 715.2 | H30: oui | I30: 1 | J30: 596 | L30: =E30/K30 -> #DIV/0! | N30: =YEAR(A30) -> 2024 | O30: =MONTH(A30) -> 4
A31: 45401 | B31: Simplon | C31: Gaetan | D31: 2024-04-19-000192 | E31: =I31*J31 -> 950 | F31: 0 | G31: =F31+E31 -> 950 | H31: oui | I31: 2 | J31: 475 | L31: =E31/K31 -> #DIV/0! | N31: =YEAR(A31) -> 2024 | O31: =MONTH(A31) -> 4
A32: 45410 | B32: Simplon | C32: Alison | D32: 2024-04-28-000193 | E32: =2*450+4*475+1*450+475/2 -> 3487.5 | F32: 0 | G32: =F32+E32 -> 3487.5 | H32: oui | I32: 6 | J32: =E32/6 -> 581.25 | L32: =E32/K32 -> #DIV/0! | N32: =YEAR(A32) -> 2024 | O32: =MONTH(A32) -> 4
A33: 45410 | B33: OpenClassrooms | C33: Alison | D33: 2024-04-28-000194 | E33: 825 | F33: =0.2*E33 -> 165 | G33: =F33+E33 -> 990 | H33: oui | I33: 6 | J33: =E33/6 -> 137.5 | L33: =E33/K33 -> #DIV/0! | N33: =YEAR(A33) -> 2024 | O33: =MONTH(A33) -> 4
A34: 45412 | B34: Aleysia | C34: Gaetan | D34: 2024-04-30-000195 | E34: =I34*J34 -> 6500 | F34: =0.2*E34 -> 1300 | G34: =F34+E34 -> 7800 | H34: oui | I34: 13 | J34: 500 | K34: 11 | L34: =E34/K34 -> 590.90909 | N34: =YEAR(A34) -> 2024 | O34: =MONTH(A34) -> 4
A35: 45418 | B35: OpenClassrooms | C35: Gaetan | D35: 2024-05-06-000196 | E35: =I35*J35 -> 410.6 | F35: =0.2*E35 -> 82.12 | G35: =F35+E35 -> 492.72 | H35: oui | I35: 1 | J35: 410.6 | L35: =E35/K35 -> #DIV/0! | N35: =YEAR(A35) -> 2024 | O35: =MONTH(A35) -> 5
A36: 45418 | B36: OpenClassrooms | C36: Alison | D36: 2024-05-06-000197 | E36: 200 | F36: =0.2*E36 -> 40 | G36: =F36+E36 -> 240 | H36: oui | I36: 2 | J36: 750 | L36: =E36/K36 -> #DIV/0! | N36: =YEAR(A36) -> 2024 | O36: =MONTH(A36) -> 5
A37: 45437.667 | B37: OpenClassrooms | C37: Alison | D37: 2024-05-26-000198 | E37: 1080 | F37: =0.2*E37 -> 216 | G37: =F37+E37 -> 1296 | H37: oui | I37: 2 | J37: 750 | L37: =E37/K37 -> #DIV/0! | N37: =YEAR(A37) -> 2024 | O37: =MONTH(A37) -> 5
A38: 45441 | B38: Sparks | C38: Alison | D38: 2024-05-29-000199 | E38: 1500 | F38: 0 | G38: =F38+E38 -> 1500 | H38: oui | I38: 2 | J38: 750 | L38: =E38/K38 -> #DIV/0! | N38: =YEAR(A38) -> 2024 | O38: =MONTH(A38) -> 5
A39: 45443 | B39: Aleysia | C39: Gaetan | D39: 2024-05-31-000200 | E39: =I39*J39 -> 7500 | F39: =0.2*E39 -> 1500 | G39: =F39+E39 -> 9000 | H39: oui | I39: 15 | J39: 500 | K39: 13 | L39: =E39/K39 -> 576.92308 | N39: =YEAR(A39) -> 2024 | O39: =MONTH(A39) -> 5
A40: 45443 | B40: Simplon | C40: Alison | D40: 2024-05-31-000201 | E40: 4612.5 | F40: 0 | G40: =F40+E40 -> 4612.5 | H40: oui | I40: 7 | J40: =E40/7 -> 658.92857 | L40: =E40/K40 -> #DIV/0! | N40: =YEAR(A40) -> 2024 | O40: =MONTH(A40) -> 5
A41: 45447 | B41: Simplon | C41: Gaetan | D41: 2024-06-04-000202 | E41: =I41*J41 -> 950 | F41: 0 | G41: =F41+E41 -> 950 | H41: oui | I41: 2 | J41: 475 | L41: =E41/K41 -> #DIV/0! | N41: =YEAR(A41) -> 2024 | O41: =MONTH(A41) -> 6
A42: 45448 | B42: OpenClassrooms | C42: Alison | D42: 2024-06-05-000203 | E42: 355 | F42: =0.2*E42 -> 71 | G42: =F42+E42 -> 426 | H42: oui | I42: 2 | J42: 750 | L42: =E42/K42 -> #DIV/0! | N42: =YEAR(A42) -> 2024 | O42: =MONTH(A42) -> 6
A43: 45448 | B43: OpenClassrooms | C43: Gaetan | D43: 2024-06-05-000204 | E43: =I43*J43 -> 650.2 | F43: =0.2*E43 -> 130.04 | G43: =F43+E43 -> 780.24 | H43: oui | I43: 1 | J43: 650.2 | L43: =E43/K43 -> #DIV/0! | N43: =YEAR(A43) -> 2024 | O43: =MONTH(A43) -> 6
A44: 45468 | B44: Sparks | C44: Alison | D44: 2024-06-25-000207 | E44: =2*800 -> 1600 | F44: 0 | G44: =F44+E44 -> 1600 | H44: oui | I44: 2 | J44: 800 | L44: =E44/K44 -> #DIV/0! | N44: =YEAR(A44) -> 2024 | O44: =MONTH(A44) -> 6
A45: 45468 | B45: Vicinity | C45: Alison | D45: 2024-06-25-000208 | E45: =I45*J45 -> 300 | F45: =0.2*E45 -> 60 | G45: =F45+E45 -> 360 | H45: oui | I45: 0.5 | J45: 600 | L45: =E45/K45 -> #DIV/0! | N45: =YEAR(A45) -> 2024 | O45: =MONTH(A45) -> 6
A46: 45470 | B46: Aleysia | C46: Gaetan | D46: 2024-06-27-000209 | E46: =I46*J46 -> 7500 | F46: =0.2*E46 -> 1500 | G46: =F46+E46 -> 9000 | H46: oui | I46: 15 | J46: 500 | K46: 12 | L46: =E46/K46 -> 625 | N46: =YEAR(A46) -> 2024 | O46: =MONTH(A46) -> 6
A47: 45473 | B47: Simplon | C47: Alison | D47: 2024-06-28-000210 | E47: =I47*J47+4*450 -> 6550 | F47: 0 | G47: =F47+E47 -> 6550 | H47: oui | I47: 10 | J47: 475 | L47: =E47/K47 -> #DIV/0! | N47: =YEAR(A47) -> 2024 | O47: =MONTH(A47) -> 6
A48: 45477 | B48: Elli Up | C48: Alison | D48: 2024-07-04-000211 | E48: =I48*J48 -> 2400 | F48: 0 | G48: =F48+E48 -> 2400 | H48: oui | I48: 2 | J48: 1200 | L48: =E48/K48 -> #DIV/0! | N48: =YEAR(A48) -> 2024 | O48: =MONTH(A48) -> 7
A49: 45478 | B49: OpenClassrooms | C49: Alison | D49: 2024-07-05-000212 | E49: =I49*J49 -> 287.5 | F49: =0.2*E49 -> 57.5 | G49: =F49+E49 -> 345 | H49: oui | I49: 1 | J49: 287.5 | L49: =E49/K49 -> #DIV/0! | N49: =YEAR(A49) -> 2024 | O49: =MONTH(A49) -> 7
A50: 45478 | B50: OpenClassrooms | C50: Gaetan | D50: 2024-07-05-000213 | E50: =I50*J50 -> 584.8 | F50: =0.2*E50 -> 116.96 | G50: =F50+E50 -> 701.76 | H50: oui | I50: 1 | J50: 584.8 | L50: =E50/K50 -> #DIV/0! | N50: =YEAR(A50) -> 2024 | O50: =MONTH(A50) -> 7
A51: 45479 | B51: Malt | C51: Gaetan | D51: 2024-07-06-000214 | E51: =I51*J51 -> 500 | F51: =0.2*E51 -> 100 | G51: =F51+E51 -> 600 | H51: oui | I51: 1 | J51: 500 | L51: =E51/K51 -> #DIV/0! | N51: =YEAR(A51) -> 2024 | O51: =MONTH(A51) -> 7
A52: 45485 | B52: Malt | C52: Gaetan | D52: 2024-07-12-000215 | E52: =I52*J52 -> 250 | F52: =0.2*E52 -> 50 | G52: =F52+E52 -> 300 | H52: oui | I52: 0.5 | J52: 500 | L52: =E52/K52 -> #DIV/0! | N52: =YEAR(A52) -> 2024 | O52: =MONTH(A52) -> 7
A53: 45495 | B53: Sparks | C53: Alison | D53: 2024-07-22-000216 | E53: =I53*J53 -> 1600 | F53: 0 | G53: =F53+E53 -> 1600 | H53: oui | I53: 2 | J53: 800 | L53: =E53/K53 -> #DIV/0! | N53: =YEAR(A53) -> 2024 | O53: =MONTH(A53) -> 7
A54: 45497 | B54: Elli Up | C54: Alison | D54: 2024-07-24-000217 | E54: =850+400 -> 1250 | F54: 0 | G54: =F54+E54 -> 1250 | H54: oui | I54: 3 | J54: 1250 | L54: =E54/K54 -> #DIV/0! | N54: =YEAR(A54) -> 2024 | O54: =MONTH(A54) -> 7
A55: 45497 | B55: Vicinity | C55: Alison | D55: 2024-07-24-000218 | E55: =I55*J55 -> 300 | F55: =0.2*E55 -> 60 | G55: =F55+E55 -> 360 | H55: oui | I55: 0.5 | J55: 600 | L55: =E55/K55 -> #DIV/0! | N55: =YEAR(A55) -> 2024 | O55: =MONTH(A55) -> 7
A56: 45497 | B56: Simplon | C56: Alison | D56: 2024-07-24-000219 | E56: =I56*J56+4*450 -> 6550 | F56: 0 | G56: =F56+E56 -> 6550 | H56: oui | I56: 10 | J56: 475 | L56: =E56/K56 -> #DIV/0! | N56: =YEAR(A56) -> 2024 | O56: =MONTH(A56) -> 7
A57: 45504 | B57: Aleysia | C57: Gaetan | D57: 2024-07-31-000220 | E57: =I57*J57 -> 9000 | F57: =0.2*E57 -> 1800 | G57: =F57+E57 -> 10800 | H57: oui | I57: 18 | J57: 500 | K57: 13 | L57: =E57/K57 -> 692.30769 | N57: =YEAR(A57) -> 2024 | O57: =MONTH(A57) -> 7
A58: 45524 | B58: OpenClassrooms | C58: Alison | D58: 2024-08-20-000221 | E58: 230 | F58: =0.2*E58 -> 46 | G58: =F58+E58 -> 276 | H58: oui | I58: 2 | J58: 750 | L58: =E58/K58 -> #DIV/0! | N58: =YEAR(A58) -> 2024 | O58: =MONTH(A58) -> 8
A59: 45530 | B59: OpenClassrooms | C59: Gaetan | D59: 2024-08-26-000222 | E59: =I59*J59 -> 307.6 | F59: =0.2*E59 -> 61.52 | G59: =F59+E59 -> 369.12 | H59: oui | I59: 1 | J59: 307.6 | L59: =E59/K59 -> #DIV/0! | N59: =YEAR(A59) -> 2024 | O59: =MONTH(A59) -> 8
A60: 45531 | B60: Simplon | C60: Alison | D60: 2024-08-27-000223 | E60: =I60*J60 -> 950 | F60: 0 | G60: =F60+E60 -> 950 | H60: oui | I60: 2 | J60: 475 | L60: =E60/K60 -> #DIV/0! | N60: =YEAR(A60) -> 2024 | O60: =MONTH(A60) -> 8
A61: 45532 | B61: Elli Up | C61: Alison | D61: 2024-08-28-000224 | E61: 400 | F61: 0 | G61: =F61+E61 -> 400 | H61: oui | I61: 0.5 | J61: 800 | L61: =E61/K61 -> #DIV/0! | N61: =YEAR(A61) -> 2024 | O61: =MONTH(A61) -> 8
A62: 45532 | B62: Vicinity | C62: Alison | D62: 2024-08-28-000225 | E62: =I62*J62 -> 300 | F62: =0.2*E62 -> 60 | G62: =F62+E62 -> 360 | H62: oui | I62: 0.5 | J62: 600 | L62: =E62/K62 -> #DIV/0! | N62: =YEAR(A62) -> 2024 | O62: =MONTH(A62) -> 8
A63: 45534 | B63: Aleysia | C63: Gaetan | D63: 2024-08-30-000226 | E63: =I63*J63 -> 3000 | F63: =0.2*E63 -> 600 | G63: =F63+E63 -> 3600 | H63: oui | I63: 6 | J63: 500 | K63: 6 | L63: =E63/K63 -> 500 | N63: =YEAR(A63) -> 2024 | O63: =MONTH(A63) -> 8
A64: 45540 | B64: OpenClassrooms | C64: Gaetan | D64: 2024-09-05-000227 | E64: =J64*I64 -> 213.6 | F64: =0.2*E64 -> 42.72 | G64: =F64+E64 -> 256.32 | H64: oui | I64: 1 | J64: 213.6 | L64: =E64/K64 -> #DIV/0! | N64: =YEAR(A64) -> 2024 | O64: =MONTH(A64) -> 9
A65: 45545 | B65: Univ Paris 1 | C65: Gaetan | D65: 2024-09-10-000228 | E65: =J65*I65+483.64 -> 13283.64 | F65: =0.2*J65*I65+48.36 -> 2608.36 | G65: =F65+E65 -> 15892 | H65: oui | I65: 16 | J65: 800 | L65: =E65/K65 -> #DIV/0! | N65: =YEAR(A65) -> 2024 | O65: =MONTH(A65) -> 9
A66: 45548 | B66: Simplon | C66: Alison | D66: 2024-09-13-000229 | E66: =I66*J66 -> 1400 | F66: 0 | G66: =F66+E66 -> 1400 | H66: oui | I66: 2 | J66: 700 | L66: =E66/K66 -> #DIV/0! | N66: =YEAR(A66) -> 2024 | O66: =MONTH(A66) -> 9
A67: 45553 | B67: Sparks | C67: Alison | D67: 2024-09-18-000230 | E67: =I67*J67 -> 1300 | F67: 0 | G67: =F67+E67 -> 1300 | H67: oui | I67: 2 | J67: 650 | L67: =E67/K67 -> #DIV/0! | N67: =YEAR(A67) -> 2024 | O67: =MONTH(A67) -> 9
A68: 45554 | B68: Simplon | C68: Alison | D68: 2024-09-19-000231 | E68: =I68*J68 -> 2375 | F68: 0 | G68: =F68+E68 -> 2375 | H68: oui | I68: 5 | J68: 475 | L68: =E68/K68 -> #DIV/0! | N68: =YEAR(A68) -> 2024 | O68: =MONTH(A68) -> 9
A69: 45565 | B69: Aleysia | C69: Gaetan | D69: 2024-09-30-000232 | E69: =I69*J69 -> 7250 | F69: =0.2*E69 -> 1450 | G69: =F69+E69 -> 8700 | H69: oui | I69: 14.5 | J69: 500 | K69: 11 | L69: =E69/K69 -> 659.09091 | N69: =YEAR(A69) -> 2024 | O69: =MONTH(A69) -> 9
A70: 45566 | B70: OnlyLyon | C70: Alison | D70: 2024-10-01-000233 | E70: =I70*J70 -> 2850 | F70: 0 | G70: =F70+E70 -> 2850 | H70: oui | I70: 3 | J70: 950 | L70: =E70/K70 -> #DIV/0! | N70: =YEAR(A70) -> 2024 | O70: =MONTH(A70) -> 10
A71: 45566 | B71: Lyria | C71: Alison | D71: 2024-10-01-000234 | E71: =I71*J71 -> 1900 | F71: 0 | G71: =F71+E71 -> 1900 | H71: oui | I71: 2 | J71: 950 | L71: =E71/K71 -> #DIV/0! | N71: =YEAR(A71) -> 2024 | O71: =MONTH(A71) -> 10
A72: 45572 | B72: OpenClassrooms | C72: Gaetan | D72: 2024-10-07-000235 | E72: =I72*J72 -> 193.4 | F72: =0.2*E72 -> 38.68 | G72: =F72+E72 -> 232.08 | H72: oui | I72: 1 | J72: 193.4 | L72: =E72/K72 -> #DIV/0! | N72: =YEAR(A72) -> 2024 | O72: =MONTH(A72) -> 10
A73: 45575 | B73: Simplon | C73: Alison | D73: 2024-10-10-000238 | E73: =I73*J73 -> 1425 | F73: 0 | G73: =F73+E73 -> 1425 | H73: oui | I73: 3 | J73: 475 | L73: =E73/K73 -> #DIV/0! | N73: =YEAR(A73) -> 2024 | O73: =MONTH(A73) -> 10
A74: 45575 | B74: Univ Paris 1 | C74: Gaetan | D74: RECTIF AVOIR | E74: -40.31 | F74: 0 | G74: 0 | H74: oui | I74: 0 | J74: 0 | L74: =E74/K74 -> #DIV/0! | N74: =YEAR(A74) -> 2024 | O74: =MONTH(A74) -> 10
A75: 45586 | B75: Elli Up | C75: Alison | D75: 2024-10-21-000239 | E75: =I75*J75 -> 800 | F75: 0 | G75: =F75+E75 -> 800 | H75: oui | I75: 1 | J75: 800 | L75: =E75/K75 -> #DIV/0! | N75: =YEAR(A75) -> 2024 | O75: =MONTH(A75) -> 10
A76: 45589 | B76: Aleysia | C76: Gaetan | D76: 2024-10-24-000240 | E76: =I76*J76 -> 7000 | F76: =0.2*E76 -> 1400 | G76: =F76+E76 -> 8400 | H76: oui | I76: 14 | J76: 500 | K76: 12 | L76: =E76/K76 -> 583.33333 | N76: =YEAR(A76) -> 2024 | O76: =MONTH(A76) -> 10
A77: 45589 | B77: Simplon | C77: Gaetan | D77: 2024-10-24-000241 | E77: =I77*J77 -> 1425 | F77: 0 | G77: =F77+E77 -> 1425 | H77: oui | I77: 3 | J77: 475 | L77: =E77/K77 -> #DIV/0! | N77: =YEAR(A77) -> 2024 | O77: =MONTH(A77) -> 10
A78: 45595 | B78: GEMA | C78: Alison | D78: 2024-10-30-000242 | E78: =I78*J78 -> 2520 | F78: 0 | G78: =F78+E78 -> 2520 | H78: oui | I78: 4 | J78: 630 | L78: =E78/K78 -> #DIV/0! | N78: =YEAR(A78) -> 2024 | O78: =MONTH(A78) -> 10
A79: 45601 | B79: OpenClassrooms | C79: Gaetan | D79: 2024-11-05-000243 | E79: =I79*J79 -> 294.7 | F79: =0.2*E79 -> 58.94 | G79: =F79+E79 -> 353.64 | H79: oui | I79: 1 | J79: 294.7 | L79: =E79/K79 -> #DIV/0! | N79: =YEAR(A79) -> 2024 | O79: =MONTH(A79) -> 11
A80: 45603 | B80: Sparks | C80: Alison | D80: 2024-11-07-000244 | E80: =I80*J80 -> 2250 | F80: 0 | G80: =F80+E80 -> 2250 | H80: oui | I80: 3 | J80: 750 | L80: =E80/K80 -> #DIV/0! | N80: =YEAR(A80) -> 2024 | O80: =MONTH(A80) -> 11
A81: 45614 | B81: Oreegami | C81: Alison | D81: 2024-11-18-000245 | E81: =I81*J81 -> 1960 | F81: =0.2*E81 -> 392 | G81: =F81+E81 -> 2352 | H81: oui | I81: 4 | J81: 490 | L81: =E81/K81 -> #DIV/0! | N81: =YEAR(A81) -> 2024 | O81: =MONTH(A81) -> 11
A82: 45616 | B82: Sparks | C82: Alison | D82: 2024-11-20-000246 | E82: =I82*J82 -> 1300 | F82: 0 | G82: =F82+E82 -> 1300 | H82: oui | I82: 2 | J82: 650 | L82: =E82/K82 -> #DIV/0! | N82: =YEAR(A82) -> 2024 | O82: =MONTH(A82) -> 11
A83: 45616 | B83: Simplon | C83: Gaetan | D83: 2024-11-20-000247 | E83: =I83*J83 -> 2375 | F83: 0 | G83: =F83+E83 -> 2375 | H83: oui | I83: 5 | J83: 475 | L83: =E83/K83 -> #DIV/0! | N83: =YEAR(A83) -> 2024 | O83: =MONTH(A83) -> 11
A84: 45624 | B84: Simplon | C84: Alison | D84: 2024-11-28-000248 | E84: =500+475 -> 975 | F84: 0 | G84: =F84+E84 -> 975 | H84: oui | I84: 1 | J84: 500 | L84: =E84/K84 -> #DIV/0! | N84: =YEAR(A84) -> 2024 | O84: =MONTH(A84) -> 11
A85: 45624 | B85: SEB | C85: Alison | D85: 2024-11-28-000249 | E85: =I85*J85 -> 8000 | F85: =0.2*E85 -> 1600 | G85: =F85+E85 -> 9600 | H85: oui | I85: 10 | J85: 800 | L85: =E85/K85 -> #DIV/0! | N85: =YEAR(A85) -> 2024 | O85: =MONTH(A85) -> 11
A86: 45624 | B86: Albert School | C86: Alison | D86: 2024-11-28-000250 | E86: =I86*J86 -> 600 | F86: 0 | G86: =F86+E86 -> 600 | H86: oui | I86: 1 | J86: 600 | L86: =E86/K86 -> #DIV/0! | N86: =YEAR(A86) -> 2024 | O86: =MONTH(A86) -> 11
A87: 45625 | B87: Aleysia | C87: Gaetan | D87: 2024-11-29-000251 | E87: =I87*J87 -> 7500 | F87: =0.2*E87 -> 1500 | G87: =F87+E87 -> 9000 | H87: oui | I87: 15 | J87: 500 | K87: 12 | L87: =E87/K87 -> 625 | N87: =YEAR(A87) -> 2024 | O87: =MONTH(A87) -> 11
A88: 45628 | B88: GL events | C88: Gaetan | D88: 2024-12-02-000252 | E88: =I88*J88 -> 5300 | F88: =0.2*E88 -> 1060 | G88: =F88+E88 -> 6360 | H88: oui | I88: 10 | J88: 530 | L88: =E88/K88 -> #DIV/0! | N88: =YEAR(A88) -> 2024 | O88: =MONTH(A88) -> 12
A89: 45628 | B89: Elli Up | C89: Alison | D89: 2024-12-02-000253 | E89: =I89*J89 -> 650 | F89: 0 | G89: =F89+E89 -> 650 | H89: oui | I89: 1 | J89: 650 | L89: =E89/K89 -> #DIV/0! | N89: =YEAR(A89) -> 2024 | O89: =MONTH(A89) -> 12
A90: 45631 | B90: OpenClassrooms | C90: Gaetan | D90: 2024-12-05-000254 | E90: =I90*J90 -> 227.4 | F90: =0.2*E90 -> 45.48 | G90: =F90+E90 -> 272.88 | H90: oui | I90: 1 | J90: 227.4 | L90: =E90/K90 -> #DIV/0! | N90: =YEAR(A90) -> 2024 | O90: =MONTH(A90) -> 12
A91: 45635 | B91: Elli Up | C91: Alison | D91: 2024-12-09-000257 | E91: =I91*J91 -> 800 | F91: 0 | G91: =F91+E91 -> 800 | H91: oui | I91: 1 | J91: 800 | L91: =E91/K91 -> #DIV/0! | N91: =YEAR(A91) -> 2024 | O91: =MONTH(A91) -> 12
A92: 45635 | B92: Elli Up | C92: Alison | D92: 2024-12-09-000255 | E92: =I92*J92 -> 230 | F92: 0 | G92: =F92+E92 -> 230 | H92: oui | I92: 1 | J92: 230 | L92: =E92/K92 -> #DIV/0! | N92: =YEAR(A92) -> 2024 | O92: =MONTH(A92) -> 12
A93: 45635 | B93: Elli Up | C93: Alison | D93: 2024-12-09-000256 | E93: =I93*J93 -> 420 | F93: 0 | G93: =F93+E93 -> 420 | H93: oui | I93: 1 | J93: 420 | L93: =E93/K93 -> #DIV/0! | N93: =YEAR(A93) -> 2024 | O93: =MONTH(A93) -> 12
A94: 45637 | B94: Elli Up | C94: Alison | D94: 2024-12-11-000258 | E94: =I94*J94+325 -> 1045 | F94: 0 | G94: =F94+E94 -> 1045 | H94: oui | I94: 1 | J94: 720 | L94: =E94/K94 -> #DIV/0! | N94: =YEAR(A94) -> 2024 | O94: =MONTH(A94) -> 12
A95: 45637 | B95: Albert School | C95: Alison | D95: 2024-12-11-000259 | E95: =I95*J95 -> 1200 | F95: 0 | G95: =F95+E95 -> 1200 | H95: oui | I95: 2 | J95: 600 | L95: =E95/K95 -> #DIV/0! | N95: =YEAR(A95) -> 2024 | O95: =MONTH(A95) -> 12
A96: 45639 | B96: Sparks | C96: Alison | D96: 2024-12-13-000260 | E96: =I96*J96 -> 1300 | F96: 0 | G96: =F96+E96 -> 1300 | H96: oui | I96: 2 | J96: 650 | L96: =E96/K96 -> #DIV/0! | N96: =YEAR(A96) -> 2024 | O96: =MONTH(A96) -> 12
A97: 45642 | B97: GL events | C97: Gaetan | D97: 2024-12-16-000261 | E97: =I97*J97 -> 5300 | F97: =0.2*E97 -> 1060 | G97: =F97+E97 -> 6360 | H97: oui | I97: 10 | J97: 530 | L97: =E97/K97 -> #DIV/0! | N97: =YEAR(A97) -> 2024 | O97: =MONTH(A97) -> 12
A98: 45644 | B98: GEMA | C98: Alison | D98: 2024-12-18-000262 | E98: =I98*J98 -> 1260 | F98: 0 | G98: =F98+E98 -> 1260 | H98: oui | I98: 2 | J98: 630 | L98: =E98/K98 -> #DIV/0! | N98: =YEAR(A98) -> 2024 | O98: =MONTH(A98) -> 12
A99: 45644 | B99: GL events | C99: Gaetan | D99: 2024-12-18-000263 | E99: =I99*J99 -> 1575 | F99: =E99*0.2 -> 315 | G99: =F99+E99 -> 1890 | H99: non | I99: 3.5 | J99: 450 | L99: =E99/K99 -> #DIV/0! | N99: =YEAR(A99) -> 2024 | O99: =MONTH(A99) -> 12
A100: 45645 | B100: Sparks | C100: Alison | D100: 2024-12-19-000264 | E100: =I100*J100 -> 800 | F100: 0 | G100: =F100+E100 -> 800 | H100: oui | I100: 1 | J100: 800 | L100: =E100/K100 -> #DIV/0! | N100: =YEAR(A100) -> 2024 | O100: =MONTH(A100) -> 12
...

Sheet Bilan 2024
C2: Réel | D2: Prev | E2: Objectif | F2: Prospection
B3: Total Recettes | C3: =SUM(C4:C5) -> 238604.03 | D3: =SUM(D4:D5) -> 238604.03 | E3: =SUM(E4:E5) -> 238604.03 | F3: =SUM(F4:F5) -> 238604.03 | I3: Salaires | J3: Prime exceptionnelle
B4: CA 2024 | C4: =SUMIFS('Factures 2024'!E:E,'Factures 2024'!H:H,"oui",'Factures 2024'!N:N,"<2025")+SUMIFS('Factures 2024'!E:E,'Factures 2024'!H:H,"non",'Factures 2024'!N:N,"<2025") -> 238604.03 | D4: =C4+SUMIFS('Factures 2024'!E:E,'Factures 2024'!H:H,"prev",'Factures 2024'!N:N,"<2025") -> 238604.03 | E4: =D4+SUMIFS('Factures 2024'!E:E,'Factures 2024'!H:H,"objectif",'Factures 2024'!N:N,"<2025") -> 238604.03 | F4: =E4+SUMIFS('Factures 2024'!E:E,'Factures 2024'!H:H,"prosp",'Factures 2024'!N:N,"<2025") -> 238604.03 | H4: Alison | I4: 4100 | J4: 4000 | R4: Somme de Montant HT | S4: Étiquettes de colonnes
B5: Divers | C5: 0 | D5: 0 | E5: 0 | F5: 0 | H5: Gaëtan | I5: =I4 -> 4100 | R5: Etiquettes de ligne | S5: prev | T5: non | U5: oui | V5: Total général
H6: Alternant | I6: 500 | J6: TJ | K6: Embauche | R6: 2024 | S6: 6000 | T6: 36325 | U6: 196279.03 | V6: 238604.03
B7: Facturé non payé | C7: =SUMIFS('Factures 2024'!E:E,'Factures 2024'!H:H,"non",'Factures 2024'!N:N,"<2025") -> 1575 | D7: HT | E7: =SUMIFS('Factures 2024'!G:G,'Factures 2024'!H:H,"non",'Factures 2024'!N:N,"<2025") -> 1890 | F7: TTC | H7: Embauche | I7: =35000/12 -> 2916.6667 | J7: 400 | R7: Trim1 | U7: 66421.5 | V7: 66421.5
H8: CA équilibre mensuel | I8: =C10/12 -> 16390.327 | J8: =D10/11.3 -> 17405.657 | K8: =I7*1.42+SUM('Charges 2024'!J:J)*1.2/12 -> 4669.8667 | R8: janv. | U8: 26596 | V8: 26596
C9: Réel | D9: Prev | E9: Objectif | F9: Prospection | H9: N mois restants | I9: 3 | R9: févr. | U9: 21283 | V9: 21283
B10: Total Dépenses | C10: =SUM(C11:C12) -> 196683.93 | D10: =SUM(D11:D12) -> 196683.93 | E10: =SUM(E11:E12) -> 196683.93 | F10: =SUM(F11:F12) -> 196683.93 | R10: mars | U10: 18542.5 | V10: 18542.5
B11: Charges globales | C11: =SUM('Charges 2024'!H:H) -> 40595.928 | D11: =C11 -> 40595.928 | E11: =D11 -> 40595.928 | F11: =E11 -> 40595.928 | R11: Trim2 | U11: 46165.2 | V11: 46165.2
B12: Salaires | C12: =1.42*((I4+I5)*12)+I6*10+2*J4*1.42 -> 156088 | D12: =C12 -> 156088 | E12: =D12 -> 156088 | F12: =E12 -> 156088 | I12: Somme de Montant HT | J12: Étiquettes de colonnes | R12: avr. | U12: 12956.9 | V12: 12956.9
I13: Etiquettes de ligne | J13: prev | K13: (vide) | L13: non | M13: oui | N13: Total général | R13: mai | U13: 15303.1 | V13: 15303.1
I14: Alison | L14: 20825 | M14: 91983.4 | N14: 112808.4 | R14: juin | U14: 17905.2 | V14: 17905.2
C15: Réel | D15: Prev | E15: Objectif | F15: Prospection | I15: Gaetan | J15: 6000 | L15: 15500 | M15: 104295.63 | N15: 125795.63 | R15: Trim3 | U15: 53732.14 | V15: 53732.14
B16: Balance | C16: =C3-C10 -> 41920.102 | D16: =D3-D10 -> 41920.102 | E16: =E3-E10 -> 41920.102 | F16: =F3-F10 -> 41920.102 | I16: (vide) | R16: juil. | U16: 22722.3 | V16: 22722.3
F17: Recrutement | I17: Total général | J17: 6000 | L17: 36325 | M17: 196279.03 | N17: 238604.03 | R17: août | U17: 5187.6 | V17: 5187.6
F18: =F16-C42-C43 -> 27910.502 | R18: sept. | U18: 25822.24 | V18: 25822.24
C19: Réel | D19: Prev | E19: Objectif | R19: Trim4 | S19: 6000 | T19: 36325 | U19: 29960.19 | V19: 72285.19
B20: Total Recettes | C20: =SUM(C21:C22) -> 238604.03 | D20: =SUM(D21:D22) -> 238604.03 | E20: =SUM(E21:E22) -> 238604.03 | I20: Somme de Montant HT | J20: Étiquettes de colonnes | R20: oct. | T20: 1900 | U20: 16173.09 | V20: 18073.09
B21: CA Alison | C21: =SUMIFS('Factures 2024'!E:E,'Factures 2024'!H:H,"oui",'Factures 2024'!N:N,"<2025",'Factures 2024'!C:C,"Alison")+SUMIFS('Factures 2024'!E:E,'Factures 2024'!H:H,"non",'Factures 2024'!N:N,"<2025",'Factures 2024'!C:C,"Alison") -> 112808.4 | D21: =C21+SUMIFS('Factures 2024'!E:E,'Factures 2024'!H:H,"prev",'Factures 2024'!N:N,"<2025",'Factures 2024'!C:C,"Alison") -> 112808.4 | E21: =D21+SUMIFS('Factures 2024'!E:E,'Factures 2024'!H:H,"objectif",'Factures 2024'!N:N,"<2025",'Factures 2024'!C:C,"Alison") -> 112808.4 | I21: Etiquettes de ligne | J21: (vide) | K21: non | L21: oui | M21: Total général | R21: nov. | T21: 14610 | U21: 10644.7 | V21: 25254.7
B22: CA Gaëtan | C22: =SUMIFS('Factures 2024'!E:E,'Factures 2024'!H:H,"oui",'Factures 2024'!N:N,"<2025",'Factures 2024'!C:C,"Gaetan")+SUMIFS('Factures 2024'!E:E,'Factures 2024'!H:H,"non",'Factures 2024'!N:N,"<2025",'Factures 2024'!C:C,"Gaetan") -> 125795.63 | D22: =C22+SUMIFS('Factures 2024'!E:E,'Factures 2024'!H:H,"prev",'Factures 2024'!N:N,"<2025",'Factures 2024'!C:C,"Gaetan") -> 125795.63 | E22: =D22+SUMIFS('Factures 2024'!E:E,'Factures 2024'!H:H,"objectif",'Factures 2024'!N:N,"<2025",'Factures 2024'!C:C,"Gaetan") -> 125795.63 | I22: Aleysia | K22: 6000 | L22: 77250 | M22: 83250 | R22: déc. | S22: 6000 | T22: 19815 | U22: 3142.4 | V22: 28957.4
I23: Simplon | K23: 6200 | L23: 45722.5 | M23: 51922.5 | R23: Total général | S23: 6000 | T23: 36325 | U23: 196279.03 | V23: 238604.03
C24: Réel | D24: Prev | E24: Ecart Objectif | F24: Ecart cumulé | I24: OpenClassrooms | L24: 16134.2 | M24: 16134.2
B25: Total | C25: =SUM(C26:C37) -> 238604.03 | D25: =SUM(D26:D37) -> 238604.03 | E25: =SUM(E26:E37) -> 41920.102 | F25: =E25 -> 41920.102 | I25: GCD | L25: 14300 | M25: 14300
B26: CA Janvier | C26: =SUMIFS('Factures 2024'!E:E,'Factures 2024'!H:H,"oui",'Factures 2024'!N:N,"<2025",'Factures 2024'!O:O,1)+SUMIFS('Factures 2024'!E:E,'Factures 2024'!H:H,"non",'Factures 2024'!N:N,"<2025",'Factures 2024'!O:O,1) -> 26596 | D26: =C26+SUMIFS('Factures 2024'!E:E,'Factures 2024'!H:H,"prev",'Factures 2024'!N:N,"<2025",'Factures 2024'!O:O,1) -> 26596 | E26: =D26-C10/11.3 -> 9190.3427 | F26: =E26 -> 9190.3427 | I26: Univ Paris 1 | L26: 13243.33 | M26: 13243.33
B27: CA Février | C27: =SUMIFS('Factures 2024'!E:E,'Factures 2024'!H:H,"oui",'Factures 2024'!N:N,"<2025",'Factures 2024'!O:O,2)+SUMIFS('Factures 2024'!E:E,'Factures 2024'!H:H,"non",'Factures 2024'!N:N,"<2025",'Factures 2024'!O:O,2) -> 21283 | D27: =C27+SUMIFS('Factures 2024'!E:E,'Factures 2024'!H:H,"prev",'Factures 2024'!N:N,"<2025",'Factures 2024'!O:O,2) -> 21283 | E27: =D27-C10/11.3 -> 3877.3427 | F27: =F26+E27 -> 13067.685 | I27: Sparks | K27: 3400 | L27: 9000 | M27: 12400
B28: CA Mars | C28: =SUMIFS('Factures 2024'!E:E,'Factures 2024'!H:H,"oui",'Factures 2024'!N:N,"<2025",'Factures 2024'!O:O,3)+SUMIFS('Factures 2024'!E:E,'Factures 2024'!H:H,"non",'Factures 2024'!N:N,"<2025",'Factures 2024'!O:O,3) -> 18542.5 | D28: =C28+SUMIFS('Factures 2024'!E:E,'Factures 2024'!H:H,"prev",'Factures 2024'!N:N,"<2025",'Factures 2024'!O:O,3) -> 18542.5 | E28: =D28-C10/11.3 -> 1136.8427 | F28: =F27+E28 -> 14204.528 | I28: GL events | K28: 12175 | M28: 12175
B29: CA Avril | C29: =SUMIFS('Factures 2024'!E:E,'Factures 2024'!H:H,"oui",'Factures 2024'!N:N,"<2025",'Factures 2024'!O:O,4)+SUMIFS('Factures 2024'!E:E,'Factures 2024'!H:H,"non",'Factures 2024'!N:N,"<2025",'Factures 2024'!O:O,4) -> 12956.9 | D29: =C29+SUMIFS('Factures 2024'!E:E,'Factures 2024'!H:H,"prev",'Factures 2024'!N:N,"<2025",'Factures 2024'!O:O,4) -> 12956.9 | E29: =D29-C10/11.3 -> -4448.7573 | F29: =F28+E29 -> 9755.7706 | I29: SEB | K29: 8000 | M29: 8000
B30: CA Mai | C30: =SUMIFS('Factures 2024'!E:E,'Factures 2024'!H:H,"oui",'Factures 2024'!N:N,"<2025",'Factures 2024'!O:O,5)+SUMIFS('Factures 2024'!E:E,'Factures 2024'!H:H,"non",'Factures 2024'!N:N,"<2025",'Factures 2024'!O:O,5) -> 15303.1 | D30: =C30+SUMIFS('Factures 2024'!E:E,'Factures 2024'!H:H,"prev",'Factures 2024'!N:N,"<2025",'Factures 2024'!O:O,5) -> 15303.1 | E30: =D30-C10/11.3 -> -2102.5573 | F30: =F29+E30 -> 7653.2133 | I30: Elli Up | K30: 230 | L30: 7765 | M30: 7995
B31: CA Juin | C31: =SUMIFS('Factures 2024'!E:E,'Factures 2024'!H:H,"oui",'Factures 2024'!N:N,"<2025",'Factures 2024'!O:O,6)+SUMIFS('Factures 2024'!E:E,'Factures 2024'!H:H,"non",'Factures 2024'!N:N,"<2025",'Factures 2024'!O:O,6) -> 17905.2 | D31: =C31+SUMIFS('Factures 2024'!E:E,'Factures 2024'!H:H,"prev",'Factures 2024'!N:N,"<2025",'Factures 2024'!O:O,6) -> 17905.2 | E31: =D31-C10/11.3 -> 499.54265 | F31: =F30+E31 -> 8152.7559 | I31: GEMA | K31: 1260 | L31: 2520 | M31: 3780
B32: CA Juillet | C32: =SUMIFS('Factures 2024'!E:E,'Factures 2024'!H:H,"oui",'Factures 2024'!N:N,"<2025",'Factures 2024'!O:O,7)+SUMIFS('Factures 2024'!E:E,'Factures 2024'!H:H,"non",'Factures 2024'!N:N,"<2025",'Factures 2024'!O:O,7) -> 22722.3 | D32: =C32+SUMIFS('Factures 2024'!E:E,'Factures 2024'!H:H,"prev",'Factures 2024'!N:N,"<2025",'Factures 2024'!O:O,7) -> 22722.3 | E32: =D32-C10/11.3 -> 5316.6427 | F32: =F31+E32 -> 13469.399 | I32: EPSI | L32: 3444 | M32: 3444
B33: CA Août | C33: =SUMIFS('Factures 2024'!E:E,'Factures 2024'!H:H,"oui",'Factures 2024'!N:N,"<2025",'Factures 2024'!O:O,8)+SUMIFS('Factures 2024'!E:E,'Factures 2024'!H:H,"non",'Factures 2024'!N:N,"<2025",'Factures 2024'!O:O,8) -> 5187.6 | D33: =C33+SUMIFS('Factures 2024'!E:E,'Factures 2024'!H:H,"prev",'Factures 2024'!N:N,"<2025",'Factures 2024'!O:O,8) -> 5187.6 | E33: =D33-C10/11.3*0.3 -> -34.097204 | F33: =F32+E33 -> 13435.301 | I33: OnlyLyon | L33: 2850 | M33: 2850
B34: CA Septembre | C34: =SUMIFS('Factures 2024'!E:E,'Factures 2024'!H:H,"oui",'Factures 2024'!N:N,"<2025",'Factures 2024'!O:O,9)+SUMIFS('Factures 2024'!E:E,'Factures 2024'!H:H,"non",'Factures 2024'!N:N,"<2025",'Factures 2024'!O:O,9) -> 25822.24 | D34: =C34+SUMIFS('Factures 2024'!E:E,'Factures 2024'!H:H,"prev",'Factures 2024'!N:N,"<2025",'Factures 2024'!O:O,9) -> 25822.24 | E34: =D34-C10/11.3 -> 8416.5827 | F34: =F33+E34 -> 21851.884 | I34: Vicinity | L34: 2700 | M34: 2700
B35: CA Octobre | C35: =SUMIFS('Factures 2024'!E:E,'Factures 2024'!H:H,"oui",'Factures 2024'!N:N,"<2025",'Factures 2024'!O:O,10)+SUMIFS('Factures 2024'!E:E,'Factures 2024'!H:H,"non",'Factures 2024'!N:N,"<2025",'Factures 2024'!O:O,10) -> 18073.09 | D35: =C35+SUMIFS('Factures 2024'!E:E,'Factures 2024'!H:H,"prev",'Factures 2024'!N:N,"<2025",'Factures 2024'!O:O,10) -> 18073.09 | E35: =D35-C10/11.3 -> 667.43265 | F35: =F34+E35 -> 22519.317 | I35: Oreegami | L35: 1960 | M35: 1960
B36: CA Novembre | C36: =SUMIFS('Factures 2024'!E:E,'Factures 2024'!H:H,"oui",'Factures 2024'!N:N,"<2025",'Factures 2024'!O:O,11)+SUMIFS('Factures 2024'!E:E,'Factures 2024'!H:H,"non",'Factures 2024'!N:N,"<2025",'Factures 2024'!O:O,11) -> 25254.7 | D36: =C36+SUMIFS('Factures 2024'!E:E,'Factures 2024'!H:H,"prev",'Factures 2024'!N:N,"<2025",'Factures 2024'!O:O,11) -> 25254.7 | E36: =D36-C10/11.3 -> 7849.0427 | F36: =F35+E36 -> 30368.359 | I36: Lyria | L36: 1900 | M36: 1900
B37: CA Décembre | C37: =SUMIFS('Factures 2024'!E:E,'Factures 2024'!H:H,"oui",'Factures 2024'!N:N,"<2025",'Factures 2024'!O:O,12)+SUMIFS('Factures 2024'!E:E,'Factures 2024'!H:H,"non",'Factures 2024'!N:N,"<2025",'Factures 2024'!O:O,12) -> 28957.4 | D37: =C37+SUMIFS('Factures 2024'!E:E,'Factures 2024'!H:H,"prev",'Factures 2024'!N:N,"<2025",'Factures 2024'!O:O,12) -> 28957.4 | E37: =D37-C10/11.3 -> 11551.743 | F37: =F36+E37 -> 41920.102 | I37: Albert School | K37: 1200 | L37: 600 | M37: 1800
I38: Malt | L38: 750 | M38: 750
I39: (vide)
B40: Recrutement | C40: Réel | D40: Prev | E40: Objectif | I40: Total général | K40: 38465 | L40: 200139.03 | M40: 238604.03
B41: Total | C41: =C44-C43-C42 -> 5994.4 | D41: =D44-D43-D42 -> 5994.4 | E41: =E44-E43-E42 -> 5994.4
B42: Salaire | C42: =I7*I9*1.42 -> 12425 | D42: =C42 -> 12425 | E42: =D42 -> 12425
B43: Charges | C43: =SUM('Charges 2024'!J:J)*1.2*I9/12 -> 1584.6 | D43: =C43 -> 1584.6 | E43: =D43 -> 1584.6
B44: CA | C44: =16.67*I9*J7 -> 20004 | D44: =C44 -> 20004 | E44: =D44 -> 20004
B45: Balance | C45: =C16+C41 -> 47914.502 | D45: =D16+D41 -> 47914.502 | E45: =E41+E16 -> 47914.502
I46: Somme de Montant HT | J46: Étiquettes de colonnes
I47: Etiquettes de ligne | J47: Alison | K47: Gaetan | L47: (vide) | M47: Total général
C48: Réel | D48: Projection | E48: Previsionnel | I48: 1 | J48: 16140 | K48: 10456 | M48: 26596
B49: Ventes | C49: ='Charges 2024'!C36-'Charges 2024'!B36 -> 186137.76 | D49: ='Charges 2024'!D36 -> 223365.31 | E49: ='Charges 2024'!E36 -> 238604.03 | I49: 2 | J49: 11845 | K49: 9438 | M49: 21283
B50: Personnel | C50: ='Charges 2024'!B35 -> 112659.63 | D50: ='Charges 2024'!D35+'Bilan 2024'!J4*2*1.42 -> 146551.56 | E50: ='Charges 2024'!E35 -> 156088 | I50: 3 | J50: 10187.5 | K50: 8355 | M50: 18542.5
B51: Achats | C51: ='Charges 2024'!B32+'Charges 2024'!B33-'Charges 2024'!C33-'Charges 2024'!C34-'Charges 2024'!C37+'Charges 2024'!B34+'Charges 2024'!B37 -> 56631.76 | D51: ='Charges 2024'!D32 -> 64263.112 | E51: ='Charges 2024'!E32 -> 40595.928 | I51: 4 | J51: 4910.9 | K51: 8046 | M51: 12956.9
B52: Solde | C52: =C49-C50-C51 -> 16846.37 | D52: =D49-D50-D51 -> 12550.644 | E52: =E49-E50-E51 -> 41920.102 | I52: 5 | J52: 7392.5 | K52: 7910.6 | M52: 15303.1
I53: 6 | J53: 8805 | K53: 9100.2 | M53: 17905.2
I54: 7 | J54: 12387.5 | K54: 10334.8 | M54: 22722.3
C55: Objectif | D55: Prospection | I55: 8 | J55: 1880 | K55: 3307.6 | M55: 5187.6
B56: Bénéfices | C56: =E16 -> 41920.102 | D56: =F16*0.85 -> 35632.087 | I56: 9 | J56: 5075 | K56: 20747.24 | M56: 25822.24
B57: Réserve | C57: =C56*E57 -> 12576.031 | D57: =D56*E57 -> 10689.626 | E57: 0.3 | I57: 10 | J57: 9495 | K57: 8578.09 | M57: 18073.09
B58: Travail | C58: =C56*E58 -> 29344.071 | D58: =D56*E58 -> 24942.461 | E58: 0.7 | I58: 11 | J58: 15085 | K58: 10169.7 | M58: 25254.7
B59: Dividendes | C59: =C56*E59*0.67*0.85 -> 0 | D59: =D56*E59*0.67*0.85 -> 0 | E59: 0 | I59: 12 | J59: 9605 | K59: 19352.4 | M59: 28957.4
B60: Moyenne associé | C60: =(C58+C59)/2 -> 14672.036 | D60: =(D58+D59)/2 -> 12471.23 | I60: (vide)
B61: IS | C61: =0.15*(E59+E58-E57)*C56 -> 2515.2061 | D61: =0.15*(E59+E58-E57)*D56 -> 2137.9252 | I61: Total général | J61: 112808.4 | K61: 125795.63 | M61: 238604.03
B62: Flat Tax | C62: =E59*C56*0.33*0.85 -> 0 | D62: =E59*D56*0.33*0.85 -> 0
A64: Sans | B64: Cotisations | C64: =C58-E58*C56*0.85/1.42 -> 11778.958 | D64: =D58-E58*D56*0.85/1.42 -> 10012.115
A65: accord | B65: IS | C65: =C56*0.15-C61 -> 3772.8092 | D65: =D56*0.15-D61 -> 3206.8878
F69: Evol benef
E70: 45419 | F70: 40813
E71: 45428 | F71: 46600
E72: 45433 | F72: 38300
E73: 45441 | F73: 47000
E74: 45454 | F74: 39500
E75: 45460 | F75: 38500
E76: 45464 | F76: 27300
E77: 45471 | F77: 29300
E78: 45476 | F78: -540
E79: 45485 | F79: -3200
E80: 45490 | F80: -2300
E81: 45495 | F81: -2600
... E98: 45635 | F98: 41900
F99: =F98 -> 41900
F100: =F99 -> 41900
F101: =F100 -> 41900
F102: =F101 -> 41900
F103: =F102 -> 41900
F104: =F103 -> 41900
F105: =F104 -> 41900
F106: =F105 -> 41900
F107: =F106 -> 41900
F108: =F107 -> 41900

Sheet Factures 2022-2023
A1: Date | B1: Client | C1: Salarié.e | D1: Numéro Facture | E1: Montant HT | F1: TVA | G1: Montant TTC | H1: Payée | Q1: Année | R1: Mois
A2: 44865 | B2: Simplon | C2: Alison | D2: 202110005 | E2: 60 | F2: 0 | G2: =F2+E2 -> 60 | H2: oui | Q2: =YEAR(A2) -> 2022 | R2: =MONTH(A2) -> 10
A3: 44865 | B3: Simplon | C3: Alison | D3: 202110006 | E3: 3600 | F3: 0 | G3: =F3+E3 -> 3600 | H3: oui | Q3: =YEAR(A3) -> 2022 | R3: =MONTH(A3) -> 10
A4: 44835 | B4: Digital Campus | C4: Gaetan | D4: 202209002 | E4: 1092 | F4: =0.2*E4 -> 218.4 | G4: =F4+E4 -> 1310.4 | H4: oui | Q4: =YEAR(A4) -> 2022 | R4: =MONTH(A4) -> 10
A5: 44847 | B5: OpenClassrooms | C5: Alison | D5: 202210001 | E5: 375 | F5: =0.2*E5 -> 75 | G5: =F5+E5 -> 450 | H5: oui | Q5: =YEAR(A5) -> 2022 | R5: =MONTH(A5) -> 10
A6: 44854 | B6: OpenClassrooms | C6: Alison | D6: 202210002 | E6: 200 | F6: =0.2*E6 -> 40 | G6: =F6+E6 -> 240 | H6: oui | Q6: =YEAR(A6) -> 2022 | R6: =MONTH(A6) -> 10
A7: 44862 | B7: Vicinity | C7: Gaetan | D7: 202210003 | E7: =450*16 -> 7200 | F7: =0.2*E7 -> 1440 | G7: =F7+E7 -> 8640 | H7: oui | Q7: =YEAR(A7) -> 2022 | R7: =MONTH(A7) -> 10
A8: 44862 | B8: Digital Campus | C8: Gaetan | D8: 202210004 | E8: 336 | F8: =0.2*E8 -> 67.2 | G8: =F8+E8 -> 403.2 | H8: oui | Q8: =YEAR(A8) -> 2022 | R8: =MONTH(A8) -> 10
A9: 44868 | B9: Sparks | C9: Alison | D9: 202211001 | E9: =650 -> 650 | F9: 0 | G9: =F9+E9 -> 650 | H9: oui | Q9: =YEAR(A9) -> 2022 | R9: =MONTH(A9) -> 11
A10: 44872 | B10: OpenClassrooms | C10: Gaetan | D10: 202211002 | E10: 640 | F10: =0.2*E10 -> 128 | G10: =F10+E10 -> 768 | H10: oui | Q10: =YEAR(A10) -> 2022 | R10: =MONTH(A10) -> 11
A11: 44872 | B11: OpenClassrooms | C11: Alison | D11: 202211003 | E11: 1295 | F11: =0.2*E11 -> 259 | G11: =F11+E11 -> 1554 | H11: oui | Q11: =YEAR(A11) -> 2022 | R11: =MONTH(A11) -> 11
A12: 44875 | B12: OpenClassrooms | C12: Alison | D12: 202211004 | E12: 375 | F12: =0.2*E12 -> 75 | G12: =F12+E12 -> 450 | H12: oui | Q12: =YEAR(A12) -> 2022 | R12: =MONTH(A12) -> 11
A13: 44893 | B13: OpenClassrooms | C13: Alison | D13: 2022-11-28-000012 | E13: 200 | F13: 40 | G13: =F13+E13 -> 240 | H13: oui | Q13: =YEAR(A13) -> 2022 | R13: =MONTH(A13) -> 11
A14: 44895 | B14: Vicinity | C14: Gaetan | D14: 2022-11-30-000013 | E14: =450*9 -> 4050 | F14: =0.2*E14 -> 810 | G14: =F14+E14 -> 4860 | H14: oui | Q14: =YEAR(A14) -> 2022 | R14: =MONTH(A14) -> 11
A15: 44895 | B15: Digital Campus | C15: Gaetan | D15: 2022-11-30-000014 | E15: =72*17.5 -> 1260 | F15: =0.2*E15 -> 252 | G15: =F15+E15 -> 1512 | H15: oui | Q15: =YEAR(A15) -> 2022 | R15: =MONTH(A15) -> 11
A16: 44900 | B16: OpenClassrooms | C16: Alison | D16: 2022-11-30-000020 | E16: 375 | F16: =0.2*E16 -> 75 | G16: =F16+E16 -> 450 | H16: oui | Q16: =YEAR(A16) -> 2022 | R16: =MONTH(A16) -> 12
A17: 44896 | B17: Simplon | C17: Alison | D17: 2022-12-01-000015 | E17: 4500 | F17: 0 | G17: =F17+E17 -> 4500 | H17: oui | Q17: =YEAR(A17) -> 2022 | R17: =MONTH(A17) -> 12
A18: 44899 | B18: Sparks | C18: Alison | D18: 2022-12-04-000016 | E18: 750 | F18: 0 | G18: 750 | H18: oui | Q18: =YEAR(A18) -> 2022 | R18: =MONTH(A18) -> 12
A19: 44900 | B19: OpenClassrooms | C19: Gaetan | D19: 2022-12-05-000017 | E19: =14*40 -> 560 | F19: =0.2*E19 -> 112 | G19: =F19+E19 -> 672 | H19: oui | Q19: =YEAR(A19) -> 2022 | R19: =MONTH(A19) -> 12
A20: 44900 | B20: OpenClassrooms | C20: Alison | D20: 2022-12-05-000018 | E20: 1115 | F20: =0.2*E20 -> 223 | G20: =F20+E20 -> 1338 | H20: oui | Q20: =YEAR(A20) -> 2022 | R20: =MONTH(A20) -> 12
A21: 44901 | B21: OpenClassrooms | C21: Alison | D21: 2022-12-06-000019 | E21: 15 | F21: =0.2*E21 -> 3 | G21: =F21+E21 -> 18 | H21: oui | Q21: =YEAR(A21) -> 2022 | R21: =MONTH(A21) -> 12
A22: 44915 | B22: PLB | C22: Alison | D22: 2022-12-20-000021 | E22: 250 | F22: =0.2*E22 -> 50 | G22: =F22+E22 -> 300 | H22: oui | Q22: =YEAR(A22) -> 2022 | R22: =MONTH(A22) -> 12
A23: 44915 | B23: Simplon | C23: Alison | D23: 2022-12-20-000022 | E23: 2700 | F23: 0 | G23: =F23+E23 -> 2700 | H23: oui | Q23: =YEAR(A23) -> 2022 | R23: =MONTH(A23) -> 12
A24: 44915 | B24: OpenClassrooms | C24: Gaetan | D24: 2022-12-20-000025 | E24: =14*40 -> 560 | F24: =0.2*E24 -> 112 | G24: =F24+E24 -> 672 | H24: oui | Q24: =YEAR(A24) -> 2022 | R24: =MONTH(A24) -> 12
A25: 44917 | B25: Digital Campus | C25: Gaetan | D25: 2022-12-22-000023 | E25: =72*3.5+24*7 -> 420 | F25: =0.2*E25 -> 84 | G25: =F25+E25 -> 504 | H25: oui | Q25: =YEAR(A25) -> 2022 | R25: =MONTH(A25) -> 12
A26: 44917 | B26: Vicinity | C26: Gaetan | D26: 2022-12-22-000024 | E26: =450*14 -> 6300 | F26: =0.2*E26 -> 1260 | G26: =F26+E26 -> 7560 | H26: oui | Q26: =YEAR(A26) -> 2022 | R26: =MONTH(A26) -> 12
A27: 44919 | B27: OpenClassrooms | C27: Alison | D27: 2022-12-24-000026 | E27: 250 | F27: =0.2*E27 -> 50 | G27: =F27+E27 -> 300 | H27: oui | Q27: =YEAR(A27) -> 2022 | R27: =MONTH(A27) -> 12
A28: 44927 | B28: OpenClassrooms | C28: Alison | D28: 2023-01-01-000027 | E28: 375 | F28: =0.2*E28 -> 75 | G28: =F28+E28 -> 450 | H28: oui | Q28: =YEAR(A28) -> 2023 | R28: =MONTH(A28) -> 1
A29: 44935 | B29: OpenClassrooms | C29: Alison | D29: 2023-01-01-000029 | E29: 375 | F29: =0.2*E29 -> 75 | G29: =F29+E29 -> 450 | H29: oui | Q29: =YEAR(A29) -> 2023 | R29: =MONTH(A29) -> 1
A30: 44932 | B30: OpenClassrooms | C30: Alison | D30: 2023-01-06-000028 | E30: 605 | F30: =0.2*E30 -> 121 | G30: =F30+E30 -> 726 | H30: oui | Q30: =YEAR(A30) -> 2023 | R30: =MONTH(A30) -> 1
A31: 44946 | B31: Simplon | C31: Gaetan | D31: 2023-01-20-000030 | E31: =450*3 -> 1350 | F31: 0 | G31: =F31+E31 -> 1350 | H31: oui | Q31: =YEAR(A31) -> 2023 | R31: =MONTH(A31) -> 1
A32: 44956 | B32: Digital Campus | C32: Gaetan | D32: 2023-01-30-000031 | E32: 1620 | F32: =0.2*E32 -> 324 | G32: =F32+E32 -> 1944 | H32: oui | Q32: =YEAR(A32) -> 2023 | R32: =MONTH(A32) -> 1
A33: 44956 | B33: Vicinity | C33: Gaetan | D33: 2023-01-30-000032 | E33: =450*12 -> 5400 | F33: =0.2*E33 -> 1080 | G33: =F33+E33 -> 6480 | H33: oui | Q33: =YEAR(A33) -> 2023 | R33: =MONTH(A33) -> 1
A34: 44956 | B34: OpenClassrooms | C34: Alison | D34: 2023-01-30-000033 | E34: 750 | F34: =0.2*E34 -> 150 | G34: =F34+E34 -> 900 | H34: oui | Q34: =YEAR(A34) -> 2023 | R34: =MONTH(A34) -> 1
A35: 44957 | B35: Simplon | C35: Alison | D35: 2023-01-31-000034 | E35: =9*450 -> 4050 | F35: 0 | G35: =F35+E35 -> 4050 | H35: oui | Q35: =YEAR(A35) -> 2023 | R35: =MONTH(A35) -> 1
A36: 44960 | B36: OpenClassrooms | C36: Gaetan | D36: 2023-02-03-000035 | E36: 700 | F36: =0.2*E36 -> 140 | G36: =F36+E36 -> 840 | H36: oui | Q36: =YEAR(A36) -> 2023 | R36: =MONTH(A36) -> 2
A37: 44962 | B37: OpenClassrooms | C37: Alison | D37: 2023-02-03-000036 | E37: 1390 | F37: =0.2*E37 -> 278 | G37: =F37+E37 -> 1668 | H37: oui | Q37: =YEAR(A37) -> 2023 | R37: =MONTH(A37) -> 2
A38: 44980 | B38: OpenClassrooms | C38: Alison | D38: 2023-02-03-000037 | E38: 390 | F38: =0.2*E38 -> 78 | G38: =F38+E38 -> 468 | H38: oui | Q38: =YEAR(A38) -> 2023 | R38: =MONTH(A38) -> 2
A39: 44980 | B39: Digital Campus | C39: Gaetan | D39: 2023-02-23-000038 | E39: =7*72 -> 504 | F39: =0.2*E39 -> 100.8 | G39: =F39+E39 -> 604.8 | H39: oui | Q39: =YEAR(A39) -> 2023 | R39: =MONTH(A39) -> 2
A40: 44980 | B40: Vicinity | C40: Gaetan | D40: 2023-02-23-000039 | E40: =450*13 -> 5850 | F40: =0.2*E40 -> 1170 | G40: =F40+E40 -> 7020 | H40: oui | Q40: =YEAR(A40) -> 2023 | R40: =MONTH(A40) -> 2
A41: 44984 | B41: OpenClassrooms | C41: Alison | D41: 2023-02-27-000040 | E41: 350 | F41: =0.2*E41 -> 70 | G41: =F41+E41 -> 420 | H41: oui | Q41: =YEAR(A41) -> 2023 | R41: =MONTH(A41) -> 2
A42: 44985 | B42: Simplon | C42: Alison | D42: 2023-02-28-000041 | E42: =4.5*450 -> 2025 | F42: 0 | G42: =F42+E42 -> 2025 | H42: oui | Q42: =YEAR(A42) -> 2023 | R42: =MONTH(A42) -> 2
A43: 44987 | B43: OpenClassrooms | C43: Alison | D43: 2023-03-02-000042 | E43: 150 | F43: =0.2*E43 -> 30 | G43: =F43+E43 -> 180 | H43: oui | Q43: =YEAR(A43) -> 2023 | R43: =MONTH(A43) -> 3
A44: 44990 | B44: Vicinity | C44: Gaetan | D44: 2023-03-05-000043 | E44: =450*3 -> 1350 | F44: =0.2*E44 -> 270 | G44: =F44+E44 -> 1620 | H44: oui | Q44: =YEAR(A44) -> 2023 | R44: =MONTH(A44) -> 3
A45: 44991 | B45: OpenClassrooms | C45: Alison | D45: 2023-03-06-000044 | E45: 1032.5 | F45: =0.2*E45 -> 206.5 | G45: =F45+E45 -> 1239 | H45: oui | Q45: =YEAR(A45) -> 2023 | R45: =MONTH(A45) -> 3
A46: 44991 | B46: OpenClassrooms | C46: Gaetan | D46: 2023-03-06-000045 | E46: 830 | F46: =0.2*E46 -> 166 | G46: =F46+E46 -> 996 | H46: oui | Q46: =YEAR(A46) -> 2023 | R46: =MONTH(A46) -> 3
A47: 44992 | B47: Sparks | C47: Alison | D47: 2023-03-07-000046 | E47: 750 | F47: 0 | G47: =F47+E47 -> 750 | H47: oui | Q47: =YEAR(A47) -> 2023 | R47: =MONTH(A47) -> 3
A48: 44992 | B48: OpenClassrooms | C48: Alison | D48: 2023-03-07-000047 | E48: 405 | F48: =0.2*E48 -> 81 | G48: =F48+E48 -> 486 | H48: oui | Q48: =YEAR(A48) -> 2023 | R48: =MONTH(A48) -> 3
A49: 45002 | B49: Digital Campus | C49: Gaetan | D49: 2023-03-17-000048 | E49: =3.5*3*72 -> 756 | F49: =0.2*E49 -> 151.2 | G49: =F49+E49 -> 907.2 | H49: oui | Q49: =YEAR(A49) -> 2023 | R49: =MONTH(A49) -> 3
A50: 45007 | B50: Simplon | C50: Alison | D50: 2023-03-22-000049 | E50: 2200 | F50: 0 | G50: =F50+E50 -> 2200 | H50: oui | Q50: =YEAR(A50) -> 2023 | R50: =MONTH(A50) -> 3
A51: 45007 | B51: Simplon | C51: Gaetan | D51: 2023-03-22-000050 | E51: 450 | F51: 0 | G51: =F51+E51 -> 450 | H51: oui | Q51: =YEAR(A51) -> 2023 | R51: =MONTH(A51) -> 3
A52: 45012 | B52: OpenClassrooms | C52: Alison | D52: 2023-03-27-000051 | E52: 250 | F52: =0.2*E52 -> 50 | G52: =F52+E52 -> 300 | H52: oui | Q52: =YEAR(A52) -> 2023 | R52: =MONTH(A52) -> 3
A53: 45014 | B53: OpenClassrooms | C53: Alison | D53: 2023-03-29-000052 | E53: 300 | F53: =0.2*E53 -> 60 | G53: =F53+E53 -> 360 | H53: oui | Q53: =YEAR(A53) -> 2023 | R53: =MONTH(A53) -> 3
A54: 45014 | B54: OpenClassrooms | C54: Alison | D54: 2023-03-29-000053 | E54: 375 | F54: =0.2*E54 -> 75 | G54: =F54+E54 -> 450 | H54: oui | Q54: =YEAR(A54) -> 2023 | R54: =MONTH(A54) -> 3
A55: 45014 | B55: Simplon | C55: Alison | D55: 2023-03-29-000054 | E55: =6*450 -> 2700 | F55: 0 | G55: =F55+E55 -> 2700 | H55: oui | Q55: =YEAR(A55) -> 2023 | R55: =MONTH(A55) -> 3
A56: 45016 | B56: Malt | C56: Gaetan | D56: 2023-03-31-000055 | E56: =427.5*15.5 -> 6626.25 | F56: =0.2*E56 -> 1325.25 | G56: =F56+E56 -> 7951.5 | H56: oui | Q56: =YEAR(A56) -> 2023 | R56: =MONTH(A56) -> 3
A57: 45016 | B57: Sparks | C57: Alison | D57: 2023-03-31-000056 | E57: =2*750 -> 1500 | F57: 0 | G57: =F57+E57 -> 1500 | H57: oui | Q57: =YEAR(A57) -> 2023 | R57: =MONTH(A57) -> 3
A58: 45021 | B58: OpenClassrooms | C58: Gaetan | D58: 2023-04-05-000057 | E58: =22*40 -> 880 | F58: =0.2*E58 -> 176 | G58: =F58+E58 -> 1056 | H58: oui | Q58: =YEAR(A58) -> 2023 | R58: =MONTH(A58) -> 4
A59: 45021 | B59: OpenClassrooms | C59: Alison | D59: 2023-04-06-000058 | E59: 725 | F59: =0.2*E59 -> 145 | G59: =F59+E59 -> 870 | H59: oui | Q59: =YEAR(A59) -> 2023 | R59: =MONTH(A59) -> 4
A60: 45040 | B60: Simplon | C60: Alison | D60: 2023-04-24-000059 | E60: 5880 | F60: 176 | G60: 6056 | H60: oui | Q60: =YEAR(A60) -> 2023 | R60: =MONTH(A60) -> 4
A61: 45041 | B61: OpenClassrooms | C61: Alison | D61: 2023-04-25-000060 | E61: 825 | F61: =0.2*E61 -> 165 | G61: =F61+E61 -> 990 | H61: oui | Q61: =YEAR(A61) -> 2023 | R61: =MONTH(A61) -> 4
A62: 45041 | B62: OpenClassrooms | C62: Alison | D62: 2023-04-25-000061 | E62: 180 | F62: =0.2*E62 -> 36 | G62: =F62+E62 -> 216 | H62: oui | Q62: =YEAR(A62) -> 2023 | R62: =MONTH(A62) -> 4
A63: 45042 | B63: Digital Campus | C63: Gaetan | D63: 2023-04-26-000062 | E63: 420 | F63: =0.2*E63 -> 84 | G63: =F63+E63 -> 504 | H63: oui | Q63: =YEAR(A63) -> 2023 | R63: =MONTH(A63) -> 4
A64: 45046 | B64: Malt | C64: Gaetan | D64: 2023-04-26-000063 | E64: =15*427.5 -> 6412.5 | F64: =0.2*E64 -> 1282.5 | G64: =F64+E64 -> 7695 | H64: oui | Q64: =YEAR(A64) -> 2023 | R64: =MONTH(A64) -> 4
A65: 45046 | B65: Malt | C65: Alison | D65: 2023-04-27-000064 | E65: 495 | F65: =0.2*E65 -> 99 | G65: =F65+E65 -> 594 | H65: oui | Q65: =YEAR(A65) -> 2023 | R65: =MONTH(A65) -> 4
A66: 45044 | B66: Simplon | C66: Alison | D66: 2023-04-28-000065 | E66: =450*5.5 -> 2475 | F66: 0 | G66: =F66+E66 -> 2475 | H66: oui | Q66: =YEAR(A66) -> 2023 | R66: =MONTH(A66) -> 4
A67: 45049 | B67: OpenClassrooms | C67: Gaetan | D67: 2023-05-03-000066 | E67: =15*40 -> 600 | F67: =0.2*E67 -> 120 | G67: =F67+E67 -> 720 | H67: oui | Q67: =YEAR(A67) -> 2023 | R67: =MONTH(A67) -> 5
A68: 45051 | B68: OpenClassrooms | C68: Gaetan | D68: 2023-05-03-000066 | E68: =15*40 -> 600 | F68: =0.2*E79 -> 1068.75 | G68: =F79+E79 -> 6412.5 | H68: oui | Q68: =YEAR(A68) -> 2023 | R68: =MONTH(A68) -> 5
A69: 45051 | B69: OpenClassrooms | C69: Alison | D69: 2023-05-05-000067 | E69: =14*40 -> 560 | F69: =0.2*E69 -> 112 | G69: =F69+E69 -> 672 | H69: oui | Q69: =YEAR(A69) -> 2023 | R69: =MONTH(A69) -> 5
A70: 45057 | B70: Simplon | C70: Alison | D70: 2023-05-11-000068 | E70: 1000 | F70: 0 | G70: =F70+E70 -> 1000 | H70: oui | Q70: =YEAR(A70) -> 2023 | R70: =MONTH(A70) -> 5
A71: 45062 | B71: Simplon | C71: Alison | D71: 2023-05-16-000069 | E71: 111.47 | F71: 0 | G71: =F71+E71 -> 111.47 | H71: oui | Q71: =YEAR(A71) -> 2023 | R71: =MONTH(A71) -> 5
A72: 45068 | B72: Digital Campus | C72: Gaetan | D72: 2023-05-22-000070 | E72: =3.5*3*72+24*3.5 -> 840 | F72: =0.2*E72 -> 168 | G72: =F72+E72 -> 1008 | H72: oui | Q72: =YEAR(A72) -> 2023 | R72: =MONTH(A72) -> 5
A73: 45068 | B73: OpenClassrooms | C73: Alison | D73: 2023-05-22-000071 | E73: 750 | F73: =0.2*E73 -> 150 | G73: =F73+E73 -> 900 | H73: oui | Q73: =YEAR(A73) -> 2023 | R73: =MONTH(A73) -> 5
A74: 45072 | B74: PLB | C74: Alison | D74: 2023-05-26-000072 | E74: 650 | F74: 0 | G74: =F74+E74 -> 650 | H74: oui | Q74: =YEAR(A74) -> 2023 | R74: =MONTH(A74) -> 5
A75: 45072 | B75: Simplon | C75: Alison | D75: 2023-05-26-000073 | E75: 550 | F75: 0 | G75: =F75+E75 -> 550 | H75: oui | Q75: =YEAR(A75) -> 2023 | R75: =MONTH(A75) -> 5
A76: 45076 | B76: OpenClassrooms | C76: Alison | D76: 2023-05-30-000074 | E76: 30 | F76: =0.2*E76 -> 6 | G76: =F76+E76 -> 36 | H76: oui | Q76: =YEAR(A76) -> 2023 | R76: =MONTH(A76) -> 5
A77: 45077 | B77: C-Libre | C77: Alison | D77: 2023-05-31-000075 | E77: 3850 | F77: =0.2*E77 -> 770 | G77: =F77+E77 -> 4620 | H77: oui | Q77: =YEAR(A77) -> 2023 | R77: =MONTH(A77) -> 5
A78: 45077 | B78: Simplon | C78: Alison | D78: 2023-05-31-000076 | E78: 2700 | F78: 0 | G78: =F78+E78 -> 2700 | H78: oui | Q78: =YEAR(A78) -> 2023 | R78: =MONTH(A78) -> 5
A79: 45077 | B79: Malt | C79: Gaetan | D79: 2023-05-31-000077 | E79: =427.5*12.5 -> 5343.75 | F79: =0.2*E79 -> 1068.75 | G79: =F79+E79 -> 6412.5 | H79: oui | Q79: =YEAR(A79) -> 2023 | R79: =MONTH(A79) -> 5
A80: 45082 | B80: Simplon | C80: Alison | D80: 2023-06-05-000078 | E80: 550 | F80: 0 | G80: =F80+E80 -> 550 | H80: oui | Q80: =YEAR(A80) -> 2023 | R80: =MONTH(A80) -> 6
A81: 45082 | B81: OpenClassrooms | C81: Gaetan | D81: 2023-06-05-000079 | E81: =16*40 -> 640 | F81: =0.2*E81 -> 128 | G81: =F81+E81 -> 768 | H81: oui | Q81: =YEAR(A81) -> 2023 | R81: =MONTH(A81) -> 6
A82: 45082 | B82: OpenClassrooms | C82: Alison | D82: 2023-06-05-000080 | E82: 800 | F82: =0.2*E82 -> 160 | G82: =F82+E82 -> 960 | H82: oui | Q82: =YEAR(A82) -> 2023 | R82: =MONTH(A82) -> 6
A83: 45099 | B83: OpenClassrooms | C83: Alison | D83: 2023-06-05-000083 | E83: 735 | F83: =0.2*E83 -> 147 | G83: =F83+E83 -> 882 | H83: oui | Q83: =YEAR(A83) -> 2023 | R83: =MONTH(A83) -> 6
A84: 45086 | B84: Simplon | C84: Alison | D84: 2023-06-09-000081 | E84: =3*450 -> 1350 | F84: 0 | G84: =F84+E84 -> 1350 | H84: oui | Q84: =YEAR(A84) -> 2023 | R84: =MONTH(A84) -> 6
A85: 45093 | B85: Simplon | C85: Alison | D85: 2023-06-16-000082 | E85: 500 | F85: 0 | G85: =F85+E85 -> 500 | H85: oui | Q85: =YEAR(A85) -> 2023 | R85: =MONTH(A85) -> 6
A86: 45099 | B86: OpenClassrooms | C86: Alison | D86: 2023-06-23-000084 | E86: 60 | F86: =0.2*E86 -> 12 | G86: =F86+E86 -> 72 | H86: oui | Q86: =YEAR(A86) -> 2023 | R86: =MONTH(A86) -> 6
A87: 45103 | B87: OpenClassrooms | C87: Alison | D87: 2023-06-26-000085 | E87: 735 | F87: =0.2*E87 -> 147 | G87: =F87+E87 -> 882 | H87: oui | Q87: =YEAR(A87) -> 2023 | R87: =MONTH(A87) -> 6
A88: 45103 | B88: Simplon | C88: Alison | D88: 2023-06-26-000086 | E88: 250 | F88: 0 | G88: =F88+E88 -> 250 | H88: oui | Q88: =YEAR(A88) -> 2023 | R88: =MONTH(A88) -> 6
A89: 45103 | B89: Digital Campus | C89: Alison | D89: 2023-06-26-000087 | E89: =4*3.5*72 -> 1008 | F89: =0.2*E89 -> 201.6 | G89: =F89+E89 -> 1209.6 | H89: oui | Q89: =YEAR(A89) -> 2023 | R89: =MONTH(A89) -> 6
A90: 45107 | B90: Digital Campus | C90: Gaetan | D90: 2023-06-30-000088 | E90: =7*3.5*72 -> 1764 | F90: =0.2*E90 -> 352.8 | G90: =F90+E90 -> 2116.8 | H90: oui | Q90: =YEAR(A90) -> 2023 | R90: =MONTH(A90) -> 6
A91: 45107 | B91: Malt | C91: Gaetan | D91: 2023-06-30-000089 | E91: =427.5*12 -> 5130 | F91: =0.2*E91 -> 1026 | G91: =F91+E91 -> 6156 | H91: oui | Q91: =YEAR(A91) -> 2023 | R91: =MONTH(A91) -> 6
A92: 45107 | B92: C-Libre | C92: Alison | D92: 2023-06-30-000090 | E92: =8*550 -> 4400 | F92: =0.2*E92 -> 880 | G92: =F92+E92 -> 5280 | H92: oui | Q92: =YEAR(A92) -> 2023 | R92: =MONTH(A92) -> 6
A93: 45112 | B93: OpenClassrooms | C93: Alison | D93: 2023-07-05-000091 | E93: 1040 | F93: =0.2*E93 -> 208 | G93: =F93+E93 -> 1248 | H93: oui | Q93: =YEAR(A93) -> 2023 | R93: =MONTH(A93) -> 7
A94: 45112 | B94: Simplon | C94: Alison | D94: 2023-07-05-000092 | E94: =500*2+300*2 -> 1600 | F94: 0 | G94: =F94+E94 -> 1600 | H94: oui | Q94: =YEAR(A94) -> 2023 | R94: =MONTH(A94) -> 7
A95: 45112 | B95: OpenClassrooms | C95: Gaetan | D95: 2023-07-05-000093 | E95: =22*40+30 -> 910 | F95: =0.2*E95 -> 182 | G95: =F95+E95 -> 1092 | H95: oui | Q95: =YEAR(A95) -> 2023 | R95: =MONTH(A95) -> 7
A96: 45114 | B96: Malt | C96: Gaetan | D96: 2023-07-07-000094 | E96: =427.5*4 -> 1710 | F96: =0.2*E96 -> 342 | G96: =F96+E96 -> 2052 | H96: oui | Q96: =YEAR(A96) -> 2023 | R96: =MONTH(A96) -> 7
A97: 45128 | B97: OpenClassrooms | C97: Alison | D97: 2023-07-21-000095 | E97: 765 | F97: =0.2*E97 -> 153 | G97: =F97+E97 -> 918 | H97: oui | Q97: =YEAR(A97) -> 2023 | R97: =MONTH(A97) -> 7
A98: 45128 | B98: OpenClassrooms | C98: Alison | D98: 2023-07-21-000096 | E98: 330 | F98: =0.2*E98 -> 66 | G98: =F98+E98 -> 396 | H98: oui | Q98: =YEAR(A98) -> 2023 | R98: =MONTH(A98) -> 7
A99: 45138 | B99: C-Libre | C99: Alison | D99: 2023-07-31-000097 | E99: =8*550 -> 4400 | F99: =0.2*E99 -> 880 | G99: =F99+E99 -> 5280 | H99: oui | Q99: =YEAR(A99) -> 2023 | R99: =MONTH(A99) -> 7
A100: 45138 | B100: Widip | C100: Alison | D100: 2023-07-31-000098 | E100: =4*700 -> 2800 | F100: =0.2*E100 -> 560 | G100: =F100+E100 -> 3360 | H100: oui | Q100: =YEAR(A100) -> 2023 | R100: =MONTH(A100) -> 7
...

Sheet Bilan 2022-2023
A2: Payé 2022-2023 | B2: =SUMIFS('Factures 2022-2023'!E:E,'Factures 2022-2023'!H:H,"oui",'Factures 2022-2023'!Q:Q,"<2024") -> 224120.1 | D2: CA prev à faire | E2: =SUMIFS('Factures 2022-2023'!E:E,'Factures 2022-2023'!H:H,"prev",'Factures 2022-2023'!Q:Q,"<2024") -> 0 | H2: Salaires | I2: =1.42*((3700*7+3800*2+5000*2+4000*3)*2)+950*6 -> 163320 | K2: =1.42*(3700*14*2+3700*12*(F8-2)) -> 147112 | N2: Somme de Montant HT | O2: Étiquettes de colonnes
A3: Impayé 2022-2023 | B3: =SUMIFS('Factures 2022-2023'!E:E,'Factures 2022-2023'!H:H,"non",'Factures 2022-2023'!Q:Q,"<2024") -> 0 | D3: CA réel | E3: =B5 -> 224120.1 | H3: Charges | I3: =SUM(H16:H27) -> 27540 | J3: =SUM(I16:I27) -> 23828 | K3: =SUM(J16:J29) -> 25852.841 | N3: Etiquettes de ligne | O3: oui | P3: Total général | T3: 2 mois de salaires + charges
A4: Impayé TTC | B4: =SUMIFS('Factures 2022-2023'!G:G,'Factures 2022-2023'!H:H,"non",'Factures 2022-2023'!Q:Q,"<2024") -> 0 | D4: Taux réalisé | E4: =E3/E5 -> 1 | F4: Taux prev | N4: 2022 | O4: 39128 | P4: 39128 | T4: =F8*3700*1.42+I3/6 -> 15098
A5: CA 2022-2023 | B5: =B3+B2 -> 224120.1 | D5: CA prev total | E5: =E2+E3 -> 224120.1 | F5: =(MONTH(TODAY())+3)/15 -> 0.4 | I5: min | J5: max | K5: avec recrutement | N5: Trim4 | O5: 39128 | P5: 39128
A6: Taux payé | B6: =B2/B5 -> 1 | H6: Bénéfice | I6: =0.85*(E5-I2-I3) -> 28271.085 | J6: =0.85*(E5-I2-J3) -> 31426.285 | K6: =0.85*(E5+F9-K2-K3) -> 43481.97 | L6: =L7+L8+L10 -> 1 | N6: oct. | O6: 12863 | P6: 12863
F7: Nb de salariés | H7: Structure | I7: =I6*L7 -> 9470.8135 | J7: =J6*L7 -> 10527.805 | K7: =K6*L7 -> 14566.46 | L7: 0.335 | N7: nov. | O7: 8470 | P7: 8470
A8: N factures payées | B8: =COUNTIF('Factures 2022-2023'!H:H,"oui") -> 153 | F8: 2 | H8: Travail | I8: =L8*I6/1.42 -> 6669.587 | J8: =L8*J6/1.42 -> 7413.9475 | K8: =L8*K6/1.42 -> 10258.07 | L8: 0.335 | N8: déc. | O8: 17795 | P8: 17795
A9: N factures non payées | B9: =COUNTIF('Factures 2022-2023'!H:H,"non") -> 0 | E9: CA recrutement 6mois | F9: =400*200*(F8-2) -> 0 | H9: Charges | I9: =I6*L8-I8 -> 2801.2265 | J9: =J6*L8-J8 -> 3113.858 | K9: =K6*L8-K8 -> 4308.3896 | N9: 2023 | O9: 184992.1 | P9: 184992.1
A10: N factures restantes | B10: =COUNTIF('Factures 2022-2023'!H:H,"prev") -> 0 | H10: Soc | I10: =I6*L10*0.7 -> 6530.6206 | J10: =J6*L10*0.7 -> 7259.4718 | K10: =K6*L10*0.7 -> 10044.335 | L10: =1-L7-L8 -> 0.33 | N10: Trim1 | O10: 45408.75 | P10: 45408.75
H11: Flat Tax | I11: =0.3*L10*I6 -> 2798.8374 | J11: =0.3*L10*J6 -> 3111.2022 | K11: =0.3*L10*K6 -> 4304.7151 | N11: janv. | O11: 14525 | P11: 14525
D12: Client | E12: CA | H12: Salaire + | I12: =I10+I8 -> 13200.208 | J12: =J10+J8 -> 14673.419 | K12: =K10+K8 -> 20302.406 | N12: févr. | O12: 11209 | P12: 11209
D13: (vide) | N13: mars | O13: 19674.75 | P13: 19674.75
D14: GTech | E14: 200 | N14: Trim2 | O14: 53799.72 | P14: 53799.72
D15: PLB | E15: 900 | J15: avec Recrutement | N15: avr. | O15: 18292.5 | P15: 18292.5
D16: GCD | E16: 1500 | G16: Etude et prestations de service | H16: ='Charges 2024'!B2 -> 8310 | I16: ='Charges 2024'!C2 -> 8310 | J16: =AVERAGE(H16:I16) -> 8310 | N16: mai | O16: 17585.22 | P16: 17585.22
D17: TGV Lyria | E17: 2400 | G17: fournitures bureau | H17: ='Charges 2024'!B3 -> 500 | I17: ='Charges 2024'!C3 -> 288 | J17: =AVERAGE(H17:I17) -> 394 | N17: juin | O17: 17922 | P17: 17922
D18: Widip | E18: 6800 | G18: Déplacements | H18: ='Charges 2024'!B4 -> 1800 | I18: ='Charges 2024'!C4 -> 1800 | J18: =AVERAGE(H18:I18)*F8/2 -> 1800 | N18: Trim3 | O18: 39345 | P18: 39345
D19: Sparks | E19: 7300 | G19: Services bancaires | H19: ='Charges 2024'!B5 -> 800 | I19: ='Charges 2024'!C5 -> 800 | J19: =AVERAGE(H19:I19) -> 800 | N19: juil. | O19: 17555 | P19: 17555
D20: Digital Campus | E20: 10270 | G20: mission/réception | H20: ='Charges 2024'!B6 -> 3000 | I20: ='Charges 2024'!C6 -> 1500 | J20: =AVERAGE(H20:I20)*F8/2 -> 2250 | N20: août | O20: 6920 | P20: 6920
D21: C-Libre | E21: 19800 | G21: téléphone/courrier | H21: ='Charges 2024'!B7 -> 1800 | I21: ='Charges 2024'!C7 -> 1800 | J21: =AVERAGE(H21:I21)*F8/2 -> 1800 | N21: sept. | O21: 14870 | P21: 14870
D22: Malt | E22: 26596.13 | G22: marketing/publicité | H22: ='Charges 2024'!B8 -> 1500 | I22: ='Charges 2024'!C8 -> 1500 | J22: =AVERAGE(H22:I22) -> 1500 | N22: Trim4 | O22: 46438.63 | P22: 46438.63
A23: Associé | B23: CA | D23: Aleysia | E23: 29250 | G23: honoraires | H23: ='Charges 2024'!B9 -> 4530 | I23: ='Charges 2024'!C9 -> 4530 | J23: =AVERAGE(H23:I23)*(F8)/2 -> 4530 | N23: oct. | O23: 16710 | P23: 16710
A24: Alison | B24: 111931.97 | D24: Vicinity | E24: 31950 | G24: cotisations | H24: ='Charges 2024'!B10 -> 1400 | I24: ='Charges 2024'!C10 -> 1400 | J24: =0.007*(E5+F9) -> 1568.8407 | N24: nov. | O24: 12735 | P24: 12735
A25: Gaetan | B25: 108188.13 | D25: OpenClassrooms | E25: 39052.5 | G25: loyer, charges, taxe foncière | H25: ='Charges 2024'!B11 -> 2400 | I25: ='Charges 2024'!C11 -> 1200 | J25: =AVERAGE(H25:I25) -> 1800 | N25: déc. | O25: 16993.63 | P25: 16993.63
A26: (vide) | D26: Simplon | E26: 48101.47 | G26: assurances | H26: ='Charges 2024'!B12 -> 1000 | I26: ='Charges 2024'!C12 -> 500 | J26: =AVERAGE(H26:I26) -> 750 | N26: Total général | O26: 224120.1 | P26: 224120.1
A27: Eliana | B27: 4000 | D27: Total général | E27: 224120.1 | G27: divers | H27: ='Charges 2024'!B13 -> 500 | I27: ='Charges 2024'!C13 -> 200 | J27: =AVERAGE(H27:I27) -> 350
A28: Total général | B28: 224120.1 | G28: prêt socoden | H28: ='Charges 2024'!B14 -> 2193.75 | I28: ='Charges 2024'!C14 -> 1755 | J28: 0
G29: prêt nef | H29: ='Charges 2024'!B15 -> 4422.5 | I29: ='Charges 2024'!C15 -> 3538 | J29: 0
A33: Bénéfices | B33: 35178.15
A34: Investissement | B34: =C34*B33 -> 11784.68 | C34: 0.335
A35: Participation | B35: =C35*B33 -> 11784.68 | C35: 0.335 | P35: oct. | Q35: 12863 | R35: =Q35/S35*100 -> 8.2185392 | S35: =39128*12/3 -> 156512
A36: Alison | B36: =(B35-B38)/2 -> 5515.8401 | C36: =B36/B35 -> 0.46805174 | P36: nov. | Q36: 8470 | R36: =Q36/S36*100 -> 5.4117256 | S36: =39128*12/3 -> 156512
A37: Gaëtan | B37: =(B35-B38)/2 -> 5515.8401 | C37: =B37/B35 -> 0.46805174 | P37: déc. | Q37: 17795 | R37: =Q37/S37*100 -> 11.369735 | S37: =39128*12/3 -> 156512
A38: Eliana | B38: 753 | C38: =B38/B35 -> 0.063896515
A39: Dividendes | B39: =B33*C39 -> 11608.79 | C39: =100%-C34-C35 -> 0.33
A40: Alison | B40: =B39*0.85*0.7/2 -> 3453.6149 | P40: janv. | Q40: 14525 | R40: =Q40/S40*100 -> 7.887443 | S40: 184153.47
A41: Gaëtan | B41: =B39*0.85*0.7/2 -> 3453.6149 | P41: févr. | Q41: 11209 | R41: =Q41/S41*100 -> 6.086771 | S41: 184153.47
P42: mars | Q42: 19674.75 | R42: =Q42/S42*100 -> 10.683888 | S42: 184153.47
A43: IS | B43: =0.15*B39 -> 1741.3184 | P43: avr. | Q43: 18292.5 | R43: =Q43/S43*100 -> 9.933291 | S43: 184153.47
P44: mai | Q44: 17585.22 | R44: =Q44/S44*100 -> 9.54922 | S44: 184153.47
A45: Total Alison | B45: =B36+B40 -> 8969.455 | P45: juin | Q45: 17922 | R45: =Q45/S45*100 -> 9.7321001 | S45: 184153.47
A46: Total Gaëtan | B46: =B37+B41 -> 8969.455 | P46: juil. | Q46: 17555 | R46: =Q46/S46*100 -> 9.5328098 | S46: 184153.47
P47: août | Q47: 6920 | R47: =Q47/S47*100 -> 3.7577353 | S47: 184153.47
P48: sept. | Q48: 14870 | R48: =Q48/S48*100 -> 8.0747868 | S48: 184153.47
P49: oct. | Q49: 16710 | R49: =Q49/S49*100 -> 9.0739534 | S49: 184153.47
P50: nov. | Q50: 12775 | R50: =Q50/S50*100 -> 6.9371487 | S50: 184153.47
P51: déc. | Q51: 16115 | R51: =Q51/S51*100 -> 8.7508533 | S51: 184153.47

Sheet Charges 2024
A1: Poste | B1: Neg 2023 | C1: Pos 2023 | E1: 2024 | G1: 2023 réel | H1: 2024 estim | J1: Recrutement | M1: Edition des Grands-Livres
A2: Etude et prestations de service | B2: =3630+1800+2880 -> 8310 | C2: =B2 -> 8310 | E2: 4000 | F2: Deplacement | G2: 2385.71 | H2: =12/15*G2 -> 1908.568 | J2: =70*12 -> 840 | M2: Date | N2: Pièce | O2: Journal | P2: Libellé | Q2: Débit | R2: Lettrage | S2: Crédit | T2: Solde
A3: fournitures bureau | B3: 500 | C3: =24*12 -> 288 | E3: 500 | F3: Reception | G3: 288.65 | H3: =100*12 -> 1200 | J3: =30*12 -> 360 | M3: Compte n°604000 | N3: Achats études et prest.serv.
A4: Déplacements | B4: =70*15+40*15+25*6 -> 1800 | C4: =B4 -> 1800 | E4: =80*12+25*12+40*12+159*12 -> 3648 | F4: Poste | G4: 26.4 | H4: =12/15*G4 -> 21.12 | M4: 45321 | N4: 1 | O4: AC | P4: ORKUN consultation en informatique | Q4: 3600 | S4: 0 | T4: 3600
A5: Services bancaires | B5: 800 | C5: =B5 -> 800 | E5: 800 | F5: Tel | G5: 469.29 | H5: =50*12 -> 600 | J5: =20*12 -> 240 | M5: 45342 | N5: 2 | O5: AC | P5: ORKUN consultation en informatique | Q5: 1600 | S5: 0 | T5: 5200
A6: mission/réception | B6: =200*15 -> 3000 | C6: =100*15 -> 1500 | E6: =200*12 -> 2400 | F6: Frais prets | G6: 193.4 | H6: =12/15*G6 -> 154.72 | M6: 45505 | N6: 202408-1 | O6: AC | P6: ALEXIS PEREZ EI génération logo de chats | Q6: 700 | S6: 0 | T6: 5900
A7: téléphone/courrier | B7: =60*15*2 -> 1800 | C7: =B7 -> 1800 | E7: =60*12 -> 720 | F7: Frais banque | G7: 335.1 | H7: =12/15*G7 -> 268.08 | M7: 45505 | N7: 202408-2 | O7: AC | P7: ALEXIS PEREZ EI création model IA de recommandatio | Q7: 3500 | S7: 0 | T7: 9400
A8: marketing/publicité | B8: 1500 | C8: =B8 -> 1500 | E8: 500 | F8: URSCOP | G8: 372 | H8: =0.007*200000+748 -> 2148 | M8: 45548 | N8: 202409-5 | O8: AC | P8: Alexis PEREZ EI crédation IA de reco GL EVENT | Q8: 1750 | S8: 0 | T8: 11150
A9: honoraires | B9: =3600+700+230 -> 4530 | C9: =B9 -> 4530 | E9: =3600+700+230 -> 4530 | F9: Recrutement | G9: 100 | H9: =12/15*G9 -> 80 | M9: Total | Q9: 11150 | S9: 0 | T9: 11150
A10: cotisations | B10: =0.007*200000 -> 1400 | C10: =B10 -> 1400 | E10: =0.007*200000 -> 1400 | F10: TR | G10: 2268 | H10: =324*6+216*6+108*3 -> 3564 | J10: =108*12 -> 1296 | M10: Compte n° 606300 | N10: Petits équipements
A11: loyer, charges, taxe foncière | B11: =400*6 -> 2400 | C11: =200*6 -> 1200 | E11: =200*12 -> 2400 | F11: WiiSmile | G11: 2548.2 | H11: =269*4+300*6+200*6+100*3 -> 4376 | J11: =89*4+100*12 -> 1556 | M11: 45322 | O11: AC | P11: NDF GCO 01 2024 souris | Q11: 191.65 | S11: 0 | T11: 191.65
A12: assurances | B12: 1000 | C12: 500 | E12: 1000 | F12: WiiSmile | G12: 590 | H12: =G12 -> 590 | J12: 150 | M12: 45322 | O12: AC | P12: NDF GCO 01 2024 clavier ducky | Q12: 189.92 | S12: 0 | T12: 381.57
A13: divers | B13: 500 | C13: 200 | E13: 500 | F13: Interet Prets | G13: 339.41 | H13: =12/15*G13 -> 271.528 | M13: 45596 | O13: AC | P13: NDF GCO 10.2024 - DARTY prises CPL | Q13: 66.66 | S13: 0 | T13: 448.23
A14: prêt socoden | B14: =1755*15/12 -> 2193.75 | C14: 1755 | E14: 1755 | F14: Presta | G14: 4800 | H14: 4000 | M14: Total | Q14: 448.23 | S14: 0 | T14: 448.23
A15: prêt nef | B15: =3538*15/12 -> 4422.5 | C15: 3538 | E15: 3538 | F15: Honoraires | G15: 3000 | H15: =618*4+1300 -> 3772 | M15: Compte n° 613200 | N15: Locations salles liées à la formation
F16: Commissions | G16: 631.8 | H16: 0 | M16: 45322 | N16: LYO04101FACLI110 | O16: AC | P16: WOJO bureau nomade | Q16: 139 | S16: 0 | T16: 139
F17: Velos | G17: 1033 | H17: =139*12 -> 1668 | J17: =70*12 -> 840 | M17: 45351 | N17: LYO04102FACLI111 | O17: AC | P17: WOJO bureau nomade | Q17: 139 | S17: 0 | T17: 278
F18: Domaine web | G18: 2046.81 | H18: =12/15*G18 -> 1637.448 | M18: 45380 | N18: LYO04103FACLI120 | O18: AC | P18: WOJO bureau nomade | Q18: 139 | S18: 0 | T18: 417
F19: Location salle | G19: 1897.66 | H19: =150*5 -> 750 | M19: 45412 | N19: LYO04103FACLI120 | O19: AC | P19: WOJO bureau nomade | Q19: 139 | S19: 0 | T19: 556
F20: Maitenance info | G20: 57.5 | H20: =12/15*G20 -> 46 | M20: 45443 | O20: AC | P20: NDF PATOU - Location salle réunion | Q20: 149 | S20: 0 | T20: 705
F21: Doc technique | G21: 23.63 | H21: =12/15*G21 -> 18.904 | M21: Total | Q21: 705 | S21: 0 | T21: 705
F22: Rémun. interm. et honoraires | G22: 3000 | H22: 0 | M22: Compte n° 613500 | N22: Locations domaine
F23: frais d'actes | G23: 203.2 | H23: =12/15*G23 -> 162.56 | M23: 45292 | N23: 2312-RCHP-000005 | O23: ODI | P23: Ext.CCA - OVH domaine scopa.co 31/03/23->16/10/24 | Q23: 668.61 | S23: 0 | T23: 668.61
F24: Sous traitance | H24: =9*400+4*400+B50+B51+B52 -> 13175 | M24: 45292 | N24: 2312-RCHP-000005 | O24: ODI | P24: Ext.CCA - NDF CONSTANT 11 2023 VPS ELITE 28/11/23- | Q24: 707.36 | S24: 0 | T24: 1375.97
F25: Location tel | H25: =23*8 -> 184 | M25: 45596 | O25: AC | P25: NDF GCO 10.2024 - OVH renouvellement scopa.co | Q25: 30.89 | S25: 0 | T25: 1406.86
F26: Frais Malt | M26: Total | Q26: 1406.86 | S26: 0 | T26: 1406.86
F27: Loyers SCI | I27: =2036*4 -> 8144 | M27: Compte n° 613510 | N27: Locations vélo
F28: Charges locaux | I28: =400*4 -> 1600 | M28: 45306 | N28: 267 | O28: AC | P28: TUTTUT location vélo 01/2024 | Q28: 166.8 | S28: 0 | T28: 166.8
M29: 45337 | N29: 291 | O29: AC | P29: TUTTUT location vélo 02 2024 | Q29: 166.8 | S29: 0 | T29: 333.6
D30: 10 | E30: mois | M30: 45366 | N30: 316 | O30: AC | P30: TUTTUT location vélo 03 2024 | Q30: 166.8 | S30: 0 | T30: 500.4
B31: Débit | C31: Crédit | D31: Projection | E31: Estim | M31: 45397 | N31: 342 | O31: AC | P31: TUTTUT location vélo 04 2024 | Q31: 166.8 | S31: 0 | T31: 667.2
A32: AC | B32: =SUMIF(O:O,A32,Q:Q) -> 34335.97 | C32: =SUMIF(O:O,A32,S:S) -> 0 | D32: =(B32+B33-C33+B34+B37-C37-C34-7500-B48)*12/D30+7500+B48 -> 64263.112 | E32: =SUM(H:H) -> 40595.928 | M32: 45427 | N32: 372 | O32: AC | P32: TUTTUT location vélo 05 2024 | Q32: 166.8 | S32: 0 | T32: 834
A33: BQ | B33: =SUMIF(O:O,A33,Q:Q) -> 489.17 | C33: =SUMIF(O:O,A33,S:S) -> 3020.23 | M33: 45458 | N33: 406 | O33: AC | P33: TUTTUT location vélo 06 2024 | Q33: 166.8 | S33: 0 | T33: 1000.8
A34: OD | B34: =SUMIF(O:O,A34,Q:Q) -> 81727.87 | C34: =SUMIF(O:O,A34,S:S) -> 59874.13 | M34: 45488 | N34: 435 | O34: AC | P34: TUTTUT location vélo 07 2024 | Q34: 166.8 | S34: 0 | T34: 1167.6
A35: PA | B35: =SUMIF(O:O,A35,Q:Q) -> 112659.63 | C35: =SUMIF(O:O,A35,S:S) -> 0 | D35: =B35*12/(D30) -> 135191.56 | E35: ='Bilan 2024'!E12 -> 156088 | M35: 45519 | N35: F00000458 | O35: AC | P35: TUTTUT location vélo 08 2024 | Q35: 166.8 | S35: 0 | T35: 1334.4
A36: VT | B36: =SUMIF(O:O,A36,Q:Q) -> 100723.14 | C36: =SUMIF(O:O,A36,S:S) -> 286860.9 | D36: =(C36-B36)*12/D30 -> 223365.31 | E36: ='Bilan 2024'!E4 -> 238604.03 | M36: 45550 | N36: 481 | O36: AC | P36: TUTTUT location vélo 09 2024 | Q36: 166.8 | S36: 0 | T36: 1501.2
A37: ODI | B37: =SUMIF(O:O,A37,Q:Q) -> 30545.61 | C37: =SUMIF(O:O,A37,S:S) -> 27572.5 | M37: 45580 | N37: 514 | O37: AC | P37: TUTTUT location vélos 10.2024 | Q37: 139 | S37: 0 | T37: 1640.2
A38: Total à date | B38: =SUM(B32:B37) -> 360481.39 | C38: =SUM(C32:C37) -> 377327.76 | M38: Total | Q38: 1640.2 | S38: 0 | T38: 1640.2
A39: Solde à date | B39: =C38-B38 -> 16846.37 | D39: =D36-D35-D32 -> 23910.644 | M39: Compte n° 613520 | N39: Locations ordinateurs
C40: Avec prime | D40: =D39-'Bilan 2024'!J4*2*1.42 -> 12550.644 | E40: =E36-E35-E32 -> 41920.102 | M40: 45294 | N40: 24010391 | O40: AC | P40: COMMOWN mensualité 01/2024 | Q40: 71.9 | S40: 0 | T40: 71.9
M41: 45325 | N41: 24023810 | O41: AC | P41: COMMOWN mensualité 02 2024 | Q41: 71.9 | S41: 0 | T41: 143.8
M42: 45354 | N42: 24037214 | O42: AC | P42: COMMOWN mensualité 03 2024 | Q42: 71.9 | S42: 0 | T42: 215.7
A43: VERIF | B43: Débit | C43: Crédit | D43: Solde | M43: 45385 | N43: 240410845 | O43: AC | P43: COMMOWN mensualité 04/2024 | Q43: 71.9 | S43: 0 | T43: 287.6
A44: Total Classe 6 | B44: 171794.55 | C44: 909.64 | D44: 170884.91 | M44: 45415 | N44: 240514451 | O44: AC | P44: COMMOWN mensualité 05/2024 | Q44: 71.9 | S44: 0 | T44: 359.5
A45: Total Classe 7 | B45: 188686.84 | C45: 376418.12 | D45: -187731.28 | M45: 45446 | N45: 240618126 | O45: AC | P45: COMMOWN location ordinateur | Q45: 95.31 | S45: 0 | T45: 454.81
B46: =B44+B45 -> 360481.39 | C46: =C44+C45 -> 377327.76 | D46: =D44+D45 -> -16846.37 | M46: 45476 | N46: 240721860 | O46: AC | P46: COMMOWN location 3 ordinateurs 07 2024 | Q46: 95.31 | S46: 0 | T46: 550.12
M47: 45507 | N47: FAC/240825604 | O47: AC | P47: COMMOWN Location ordinateur 08 2024 | Q47: 95.31 | S47: 0 | T47: 645.43
A48: TOTAL | B48: =SUM(B49:B54) -> 10975 | M48: 45538 | N48: FAC/240825604 | O48: AC | P48: COMMOWN Location ordinateur 09 2024 | Q48: 95.31 | S48: 0 | T48: 740.74
A49: Qualiopi | B49: 3000 | M49: 45568 | N49: 241033383 | O49: AC | P49: COMMOWN - Location ordi 10.2024 | Q49: 95.31 | S49: 0 | T49: 836.05
A50: Presta Alexis P GL Events | B50: =15*350+3.5*350 -> 6475 | M50: Total | Q50: 836.05 | S50: 0 | T50: 836.05
A51: Presta Alexis P Cats | B51: =1.5*350+0.5*350 -> 700 | M51: Compte n° 615600 | N51: Maintenance informatique
A52: Presta Orkun | B52: 800 | M52: 45292 | N52: 2312-RCHP-000005 | O52: ODI | P52: Ext.CCA - NDF 08 2023 APA Abo Microsoft 16/08/23-> | Q52: 35.82 | S52: 0 | T52: 35.82
M53: 45371 | N53: 202401 | O53: AC | P53: HABILE abo service numérique Cloud 117 | Q53: 84.6 | S53: 0 | T53: 120.42
M54: 45461 | N54: 7806343 | O54: AC | P54: Kahoot logiciel d'apprentissage 18/06/24->18/05/25 | Q54: 115.06 | S54: 0 | T54: 235.48
M55: 45504 | O55: AC | P55: NDF GCO 07 2024 Abo OpenIA | Q55: 5 | S55: 0 | T55: 240.48
M56: 45596 | O56: AC | P56: NDF GCO 10.2024 -abo Proton AG | Q56: 287.88 | S56: 0 | T56: 528.36
M57: Total | Q57: 528.36 | S57: 0 | T57: 528.36
M58: Compte n° 616000 | N58: Primes d'assurance
M59: 45292 | N59: 2312-RCHP-000006 | O59: ODI | P59: Ext.CCA - STELLO assurance civile pro 05/09/2023-> | Q59: 99.78 | S59: 0 | T59: 99.78
M60: 45292 | N60: 2312-RCHP-000006 | O60: ODI | P60: Ext.CCA - NDF APA 10 2023 assuranc stello 02/01/24 | Q60: 32.91 | S60: 0 | T60: 132.69
M61: 45536 | N61: 66D3B8585FB76 | O61: AC | P61: STELLO assurance civile pro 01/09/24 - 31/08/25 | Q61: 250.8 | S61: 0 | T61: 383.49
M62: Total | Q62: 383.49 | S62: 0 | T62: 383.49
M63: Compte n° 618300 | N63: Documentation technique
M64: 45473 | O64: AC | P64: NDF GCO 06 2024 Hors serie Havard Review IA | Q64: 19.59 | S64: 0 | T64: 19.59
M65: Total | Q65: 19.59 | S65: 0 | T65: 19.59
M66: Compte n° 622200 | N66: Commission et courtage sur ventes
M67: 45322 | O67: AC | P67: SWILE ticket restaurant 01/2024 | Q67: 0.3 | S67: 0 | T67: 0.3
M68: 45348 | O68: AC | P68: SWILE ticket restaurant 02 2024 | Q68: 0.3 | S68: 0 | T68: 0.6
M69: 45370 | O69: AC | P69: SWILE ticket restaurant 03 2024 | Q69: 0.3 | S69: 0 | T69: 0.9
M70: 45401 | O70: AC | P70: SWILE ticket restaurant 04 2024 | Q70: 0.3 | S70: 0 | T70: 1.2
M71: 45443 | N71: 2024-005 | O71: AC | P71: SWILE - ticket restaurant 05/2024 | Q71: 0.3 | S71: 0 | T71: 1.5
M72: 45457 | N72: MFEZ-2024-006 | O72: AC | P72: SWILE rechargement ticket restaurant | Q72: 0.1 | S72: 0 | T72: 1.6
M73: 45473 | N73: MFEZ-2024-007 | O73: AC | P73: SWILE ticket restaurant | Q73: 0.2 | S73: 0 | T73: 1.8
M74: 45479 | N74: 24073187 | O74: AC | P74: MALT commission malt veille pour génération images | Q74: 50 | S74: 0 | T74: 51.8
M75: 45485 | N75: 24074873 | O75: AC | P75: MALT commission mini appli pour générer des images | Q75: 25 | S75: 0 | T75: 76.8
M76: 45504 | N76: 2024-008 | O76: AC | P76: SWILE ticket restaurant | Q76: 0.2 | S76: 0 | T76: 77
M77: 45535 | N77: INV-MFEZ-2024-09 | O77: AC | P77: SWILE ticket restaurant | Q77: 0.2 | S77: 0 | T77: 77.2
M78: 45565 | N78: 2024-010 | O78: AC | P78: SWILE ticket restaurant | Q78: 0.3 | S78: 0 | T78: 77.5
M79: 45596 | N79: MV-INV-MFEZ-2024 | O79: AC | P79: SWILE - tickets resto 10.2024 | Q79: 0.3 | S79: 0 | T79: 77.8
M80: Total | Q80: 77.8 | S80: 0 | T80: 77.8
M81: Compte n° 622600 | N81: Honoraires comptable
M82: 45322 | N82: VIL060584 | O82: AC | P82: ODICEO presta compta acompte N°1 | Q82: 618 | S82: 0 | T82: 618
M83: 45382 | N83: VIL062224 | O83: AC | P83: ODICEO 2 777 + regul hono 31 12 2023 | Q83: 1300 | S83: 0 | T83: 1918
M84: 45412 | N84: VIL062390 | O84: AC | P84: ODICEO acompte presta compta N°2 | Q84: 618 | S84: 0 | T84: 2536
M85: 45504 | N85: VIL064669 | O85: AC | P85: ODICEO acompte N° 3 2024 | Q85: 618 | S85: 0 | T85: 3154
M86: 45596 | N86: VIL065956 | O86: AC | P86: ODICEO - Acompte compta n°4 | Q86: 618 | S86: 0 | T86: 3772
M87: Total | Q87: 3772 | S87: 0 | T87: 3772
M88: Compte n° 622620 | N88: Honoraires révision coopérative
M89: 45292 | N89: FNP | O89: OD | P89: révision SCOP | Q89: 0 | S89: 748 | T89: -748
M90: 45377 | N90: 2024/03/1240 | O90: AC | P90: AUREV révision coopérative 31/12/2023 | Q90: 523.6 | S90: 0 | T90: -224.4
M91: Total | Q91: 523.6 | S91: 748 | T91: -224.4
M92: Compte n° 622630 | N92: Honoraires divers
M93: 45356 | N93: FC2413815 | O93: AC | P93: QUALITIA certification QUALIOPI | Q93: 333.33 | S93: 0 | T93: 333.33
M94: 45480 | N94: FA2407-0442 | O94: AC | P94: OPENS accompagnement certif QUALIOPI | Q94: 1900 | S94: 0 | T94: 2233.33
M95: 45509 | N95: FC2416500 | O95: AC | P95: QUALITIA certification QUALIOPI audit | Q95: 666.67 | S95: 0 | T95: 2900
M96: Total | Q96: 2900 | S96: 0 | T96: 2900
M97: Compte n° 623400 | N97: Cadeaux à la clientèle
M98: 45546 | N98: 240240 | O98: AC | P98: Vins Bulliat Daniel Régis | Q98: 100 | S98: 0 | T98: 100
M99: Total | Q99: 100 | S99: 0 | T99: 100
M100: Compte n° 625100 | N100: Frais de déplacement
...

Sheet Prev
A1: Date | B1: Client | C1: Salarié.e | D1: Montant HT | E1: Jours | F1: TJ
A2: 45746 | B2: Albert School | C2: Alison | D2: =90*7*3 -> 1890 | E2: 2 | F2: =D2/E2 -> 945 | G2: 945 | I2: Réel
A3: 45777 | B3: Albert School | C3: Alison | D3: =3*90*3 -> 810 | E3: 1 | F3: =3*90*3 -> 810 | G3: 810 | H3: Total Recettes | I3: =SUM(I4:I5) -> 252490
A4: 45807 | B4: Albert School | C4: Alison | D4: =3*5*90 -> 1350 | E4: 2 | F4: =D4/E4 -> 675 | G4: 675 | H4: CA 2024 | I4: =SUM(D:D) -> 247990
A5: 45688 | B5: Elli Up | C5: Alison | D5: =E5*F5 -> 950 | E5: 2 | F5: 475 | H5: Divers | I5: 4500
A6: 45746 | B6: GEMA | C6: Alison | D6: =1890 -> 1890 | E6: 2 | F6: =D6/E6 -> 945 | G6: 945
A7: 45688 | B7: Mission Alison | C7: Alison | D7: =E7*F7 -> 7800 | E7: 13 | F7: 600 | I7: Réel
A8: 45716 | B8: Mission Alison | C8: Alison | D8: =E8*F8 -> 7800 | E8: 13 | F8: 600 | H8: Total Dépenses | I8: =SUM(I9:I10) -> 191508
A9: 45746 | B9: Mission Alison | C9: Alison | D9: =E9*F9 -> 7800 | E9: 13 | F9: 600 | H9: Charges globales | I9: 30000
A10: 45777 | B10: Mission Alison | C10: Alison | D10: =E10*F10 -> 7800 | E10: 13 | F10: 600 | H10: Salaires | I10: =1.42*2*4100*12+9000+1.42*3000*3 -> 161508
A11: 45807 | B11: Mission Alison | C11: Alison | D11: =E11*F11 -> 7800 | E11: 13 | F11: 600
A12: 45838 | B12: Mission Alison | C12: Alison | D12: =E12*F12 -> 7800 | E12: 13 | F12: 600 | I12: Réel
A13: 45868 | B13: Mission Alison | C13: Alison | D13: =E13*F13 -> 7800 | E13: 13 | F13: 600 | H13: Balance | I13: =I3-I8 -> 60982
A14: 45899 | B14: Mission Alison | C14: Alison | D14: =E14*F14 -> 7800 | E14: 13 | F14: 600
A15: 45930 | B15: Mission Alison | C15: Alison | D15: =E15*F15 -> 7800 | E15: 13 | F15: 600
A16: 45960 | B16: Mission Alison | C16: Alison | D16: =E16*F16 -> 7800 | E16: 13 | F16: 600
A17: 45991 | B17: Mission Alison | C17: Alison | D17: =E17*F17 -> 7800 | E17: 13 | F17: 600 | I17: Réel
A18: 46021 | B18: Mission Alison | C18: Alison | D18: =E18*F18 -> 7800 | E18: 13 | F18: 600 | H18: Total Recettes | I18: =SUM(I19:I20) -> 229090
A19: 45688 | B19: Simplon | C19: Alison | D19: =E19*F19 -> 950 | E19: 2 | F19: 475 | H19: CA Alison | I19: =SUMIFS(D:D,C:C,"Alison") -> 118490
A20: 45716 | B20: Simplon | C20: Alison | D20: =E20*F20 -> 950 | E20: 2 | F20: 475 | H20: CA Gaëtan | I20: =SUMIFS(D:D,C:C,"Gaetan") -> 110600
A21: 45746 | B21: Simplon | C21: Alison | D21: =E21*F21 -> 950 | E21: 2 | F21: 475 | H21: CA Autre | I21: =I4-I18 -> 18900
A22: 45777 | B22: Simplon | C22: Alison | D22: =E22*F22 -> 950 | E22: 2 | F22: 475
A23: 45777 | B23: White Mirror | C23: Alison | D23: 900 | E23: 1 | F23: 900
A24: 45688 | B24: Aleysia | C24: Gaetan | D24: =E24*F24 -> 7000 | E24: 14 | F24: 500
A25: 45716 | B25: Aleysia | C25: Gaetan | D25: =E25*F25 -> 7000 | E25: 14 | F25: 500
A26: 45746 | B26: Aleysia | C26: Gaetan | D26: =E26*F26 -> 7000 | E26: 14 | F26: 500
A27: 45777 | B27: Aleysia | C27: Gaetan | D27: =E27*F27 -> 7000 | E27: 14 | F27: 500
A28: 45807 | B28: Aleysia | C28: Gaetan | D28: =E28*F28 -> 3000 | E28: 6 | F28: 500
A29: 45838 | B29: Aleysia | C29: Gaetan | D29: =E29*F29 -> 7000 | E29: 14 | F29: 500
A30: 45868 | B30: Aleysia | C30: Gaetan | D30: =E30*F30 -> 7000 | E30: 14 | F30: 500
A31: 45899 | B31: Aleysia | C31: Gaetan | D31: =E31*F31 -> 7000 | E31: 14 | F31: 500
A32: 45930 | B32: Mission Gaetan | C32: Gaetan | D32: =E32*F32 -> 7700 | E32: 14 | F32: 550
A33: 45960 | B33: Mission Gaetan | C33: Gaetan | D33: =E33*F33 -> 7700 | E33: 14 | F33: 550
A34: 45991 | B34: Mission Gaetan | C34: Gaetan | D34: =E34*F34 -> 7700 | E34: 14 | F34: 550
A35: 46021 | B35: Mission Gaetan | C35: Gaetan | D35: =E35*F35 -> 7700 | E35: 14 | F35: 550
... A47: 45688 | B47: Jtekt | C47: Alison | D47: =E47*F47 -> 12000 | E47: 15 | F47: 800
A48: 45688 | B48: Elli Up | C48: Alison | D48: =2*650 -> 1300 | E48: 2 | F48: 650
A49: 45688 | B49: Plouf Altea | C49: Gaetan | D49: =E49*F49 -> 5000 | E49: 1 | F49: 5000
A50: 45688 | B50: Univ Paris 1 | C50: Gaetan | D50: =E50*F50 -> 9750 | E50: 15 | F50: 650

Sheet Détails1
A1: Détails pou for Somme de Montant HT - Salarié.e : Gaetan
A3: Date | B3: Client | C3: Salarié.e | D3: Numéro Facture | E3: Montant HT | F3: TVA | G3: Montant TTC | H3: Payée | I3: Jours facturés | J3: TJf
A4: 45473 | B4: Plouf | C4: Gaetan | E4: 0 | F4: 0 | G4: 0 | H4: objectif | I4: 0 | J4: 5000
A5: 45359 | B5: Simplon | C5: Gaetan | D5: 2024-03-08-000175 | E5: 475 | F5: 0 | G5: 475 | H5: non | I5: 1 | J5: 475
A6: 45631 | B6: OpenClassrooms | C6: Gaetan | E6: 480 | F6: 96 | G6: 576 | H6: prev | I6: 1 | J6: 480
A7: 45606 | B7: OpenClassrooms | C7: Gaetan | E7: 480 | F7: 96 | G7: 576 | H7: prev | I7: 1 | J7: 480
A8: 45575 | B8: OpenClassrooms | C8: Gaetan | E8: 480 | F8: 96 | G8: 576 | H8: prev | I8: 1 | J8: 480
A9: 45544 | B9: OpenClassrooms | C9: Gaetan | E9: 480 | F9: 96 | G9: 576 | H9: prev | I9: 1 | J9: 480
A10: 45513 | B10: OpenClassrooms | C10: Gaetan | E10: 480 | F10: 96 | G10: 576 | H10: prev | I10: 1 | J10: 480
A11: 45482 | B11: OpenClassrooms | C11: Gaetan | E11: 480 | F11: 96 | G11: 576 | H11: prev | I11: 1 | J11: 480
A12: 45451 | B12: OpenClassrooms | C12: Gaetan | E12: 480 | F12: 96 | G12: 576 | H12: prev | I12: 1 | J12: 480
A13: 45389 | B13: OpenClassrooms | C13: Gaetan | E13: 480 | F13: 96 | G13: 576 | H13: prev | I13: 1 | J13: 480
A14: 45420 | B14: OpenClassrooms | C14: Gaetan | E14: 480 | F14: 96 | G14: 576 | H14: prev | I14: 1 | J14: 480
A15: 45296 | B15: OpenClassrooms | C15: Gaetan | D15: 2024-01-05-000151 | E15: 660 | F15: 132 | G15: 792 | H15: oui | I15: 1 | J15: 660
A16: 45327 | B16: OpenClassrooms | C16: Gaetan | D16: 2024-02-05-000164 | E16: 790 | F16: 158 | G16: 948 | H16: oui | I16: 1 | J16: 790
A17: 45356 | B17: OpenClassrooms | C17: Gaetan | D17: 2024-03-05-000173 | E17: 880 | F17: 176 | G17: 1056 | H17: oui | I17: 1 | J17: 880
A18: 45473 | B18: Simplon | C18: Gaetan | E18: 950 | F18: 0 | G18: 950 | H18: prev | I18: 2 | J18: 475
A19: 45412 | B19: Simplon | C19: Gaetan | E19: 950 | F19: 0 | G19: 950 | H19: prev | I19: 2 | J19: 475
A20: 45345 | B20: EPSI | C20: Gaetan | D20: 2024-02-23-000165 | E20: 1148 | F20: 0 | G20: 1148 | H20: non | I20: 2 | J20: 574
A21: 45530.667 | B21: Mission Gaetan | C21: Gaetan | E21: 2000 | F21: 400 | G21: 2400 | H21: objectif | I21: 4 | J21: 500
A22: 45314 | B22: EPSI | C22: Gaetan | D22: 2024-01-23-000157 | E22: 2296 | F22: 0 | G22: 2296 | H22: oui | I22: 4 | J22: 574
A23: 45650.667 | B23: Mission Gaetan | C23: Gaetan | E23: 6000 | F23: 1200 | G23: 7200 | H23: objectif | I23: 12 | J23: 500
A24: 45620.667 | B24: Mission Gaetan | C24: Gaetan | E24: 6000 | F24: 1200 | G24: 7200 | H24: objectif | I24: 12 | J24: 500
A25: 45590.667 | B25: Mission Gaetan | C25: Gaetan | E25: 6000 | F25: 1200 | G25: 7200 | H25: objectif | I25: 12 | J25: 500
A26: 45560.667 | B26: Mission Gaetan | C26: Gaetan | E26: 6000 | F26: 1200 | G26: 7200 | H26: objectif | I26: 12 | J26: 500
A27: 45500.667 | B27: Mission Gaetan | C27: Gaetan | E27: 6000 | F27: 1200 | G27: 7200 | H27: objectif | I27: 12 | J27: 500
A28: 45470.667 | B28: Aleysia | C28: Gaetan | E28: 6000 | F28: 1200 | G28: 7200 | H28: prev | I28: 12 | J28: 500
A29: 45440.667 | B29: Aleysia | C29: Gaetan | E29: 6000 | F29: 1200 | G29: 7200 | H29: prev | I29: 12 | J29: 500
A30: 45381 | B30: Aleysia | C30: Gaetan | E30: 7000 | F30: 1400 | G30: 8400 | H30: prev | I30: 14 | J30: 500
A31: 45410.667 | B31: Aleysia | C31: Gaetan | E31: 7000 | F31: 1400 | G31: 8400 | H31: prev | I31: 14 | J31: 500
A32: 45351 | B32: Aleysia | C32: Gaetan | D32: 2024-02-29-000171 | E32: 7500 | F32: 1500 | G32: 9000 | H32: non | I32: 15 | J32: 500
A33: 45322 | B33: Aleysia | C33: Gaetan | D33: 2024-01-31-000162 | E33: 7500 | F33: 1500 | G33: 9000 | H33: oui | I33: 15 | J33: 500
A34: 45443 | B34: Univ Paris 1 | C34: Gaetan | E34: 12800 | F34: 2560 | G34: 15360 | H34: prev | I34: 16 | J34: 800
A35: 45657 | B35: Gaetan full time | C35: Gaetan | E35: 18000 | F35: 3600 | G35: 21600 | H35: objectif | I35: 36 | J35: 500

Sheet Salaries
A1: Salarie | B1: Salaire | C1: TJM | D1: ETP
A2: Gaetan | B2: 63428.57 | C2: 510 | D2: 3.5
A3: Alison | B3: 63428.57 | C3: 510 | D3: 3.5
A4: Recrutement 1 | B4: 35000 | C4: 500 | D4: 5
A5: Recrutement 2 | B5: 35000 | C5: 500 | D5: 5
A6: Recrutement 3 | B6: 35000 | C6: 500 | D6: 5

Sheet Feuil1
E4: TJM | F4: =105000/SUM(D6:D17) -> 719.17808
D5: Jfactu
C6: Octobre | D6: 16 | I6: BP25
C7: Novembre | D7: 9 | H7: Dépenses | I7: Recettes | K7: 2023 | L7: 2024
C8: Décembre | D8: 14 | G8: Salaires | H8: =4100*12*1.42*2 -> 139728 | I8: CA Gaëtan | J8: =(K8+L8)/2 -> 88200 | K8: =108000*12/15 -> 86400 | L8: 90000
C9: Janvier | D9: 12 | G9: Charges | H9: 25000 | I9: CA Alison | J9: =(K9+L9)/2 -> 84000 | K9: =110000*12/15 -> 88000 | L9: =80000 -> 80000
C10: février | D10: 13 | G10: Alternance | H10: =500*12 -> 6000
C11: Mars | D11: 18.5 | G11: Prêt | H11: =2400*12 -> 28800 | I11: Loyers | J11: =6*200*12*0.8 -> 11520
C12: Avril | D12: 15
C13: Mai | D13: 12.5
C14: Juin | D14: 12 | G14: Total | H14: =SUM(H8:H13) -> 199528 | I14: Total | J14: =SUM(J8:J13) -> 183720 | N14: prime | O14: =O15/12*0.25 -> 729.16667
C15: Juillet | D15: 4 | N15: salaire brut | O15: =35000 -> 35000
C16: Août | D16: 7 | H16: Balance | I16: =J14-H14 -> -15808 | N16: charges | O16: 6000
C17: Septembre | D17: 13 | N17: benefices | O17: 10000 | Q17: =Q18-(O15+O14)*1.42-O16 -> 13264.583
P18: =(O14+O15)*1.42+O16+O17 -> 66735.417 | Q18: =Q19*200 -> 70000
P19: =P18/200 -> 333.67708 | Q19: 350
C24: Objectif | H24: 124.55 | I24: =H24*1.1 -> 137.005 | J24: =I24/1.2 -> 114.17083 | K24: =J24*1.2 -> 137.005
B25: Bénéfices | C25: 41000 | H25: 198.18 | I25: =H25*1.1 -> 217.998 | J25: =I25/1.2 -> 181.665 | K25: =J25*1.2 -> 217.998
B26: Réserve | C26: =(C25-C30)*D26 -> 11562 | D26: 0.3 | H26: 160.91 | I26: =H26*1.1 -> 177.001 | J26: =I26/1.2 -> 147.50083 | K26: =J26*1.2 -> 177.001
B27: Travail | C27: =(C25-C30)*D27 -> 16186.8 | D27: 0.42 | H27: =SUM(H24:H26) -> 483.64 | I27: =SUM(I24:I26) -> 532.004 | J27: =SUM(J24:J26) -> 443.33667 | K27: =J27*1.2 -> 532.004
B28: Dividendes | C28: =(C25-C30)*D28*0.7 -> 7553.84 | D28: 0.28
B30: IS | C30: =0.15*(D28+D27-D26)*C25 -> 2460 | E30: Réserve | F30: 0.4 | G30: 0.3 | H30: 0.335 | I30: 0.35 | J30: 0.3 | M30: 6000
B31: Flat Tax | C31: =D28*(C25-C30)*0.3 -> 3237.36 | E31: Travail | F31: 0.6 | G31: 0.7 | H31: 0.335 | I31: 0.65 | J31: 0.42 | N31: =270*3.5*52 -> 49140
E32: Dividendes | F32: 0 | G32: 0 | H32: 0.33 | I32: 0 | J32: 0.28 | N32: =N31-M30 -> 43140
E33: Dividendes | F33: 0 | G33: 0 | H33: 7684 | I33: 0 | J33: 7553 | N33: =N32/1.42 -> 30380.282
E34: Travail | F34: 20370 | G34: 23030 | H34: 11144 | I34: 21726 | J34: 16186 | N34: =33000*1.42 -> 46860
E35: A & G Travail | F35: =F34/2 -> 10185 | G35: =G34/2 -> 11515 | H35: =H34/2 -> 5572 | I35: =I34/2 -> 10863 | J35: =J34/2 -> 8093
E36: A & G bloque | F36: =F34/2-F41 -> 8669 | G36: =G34/2-G41 -> 9747 | H36: =H34/2-H41 -> 4726 | I36: =I34/2-I41 -> 9221 | J36: =J34/2-J41 -> 6893
E37: SCOPA | F37: 13580 | G37: 9870 | H37: 11144 | I37: 11698 | J37: 11562
E38: IS | F38: 1050 | G38: 2100 | H38: 1732 | I38: 1575 | J38: 2460
E39: Flat Tax | F39: 0 | G39: 0 | H39: 3293 | I39: 0 | J39: 3237
E40: IR | F40: =0.3*F35 -> 3055.5 | G40: =0.3*G35 -> 3454.5 | H40: =0.3*H35 -> 1671.6 | I40: =0.3*I35 -> 3258.9 | J40: =0.3*J35 -> 2427.9
E41: Salaries | F41: 1516 | G41: 1768 | H41: 846 | I41: 1642 | J41: 1200
E42: Gaetan direct | F42: =(F35-F40+F33)/2 -> 3564.75 | G42: =(G35-G40+G33)/2 -> 4030.25 | H42: =(H35-H40+H33)/2 -> 5792.2 | I42: =(I35-I40+I33)/2 -> 3802.05 | J42: =(J35-J40+J33)/2 -> 6609.05
E43: Alison direct | F43: =(F35-F40+F33)/2 -> 3564.75 | G43: =(G35-G40+G33)/2 -> 4030.25 | H43: =(H35-H40+H33)/2 -> 5792.2 | I43: =(I35-I40+I33)/2 -> 3802.05 | J43: =(J35-J40+J33)/2 -> 6609.05
E44: Argent perdu | F44: =F41+F40+F39+F38 -> 5621.5 | G44: =G41+G40+G39+G38 -> 7322.5 | H44: =H41+H40+H39+H38 -> 7542.6 | I44: =I41+I40+I39+I38 -> 6475.9 | J44: =J41+J40+J39+J38 -> 9324.9
F46: =F44+F43+F42+F37+F36 -> 35000 | G46: =G44+G43+G42+G37+G36 -> 35000 | H46: =H44+H43+H42+H37+H36 -> 34997 | I46: =I44+I43+I42+I37+I36 -> 34999 | J46: =J44+J43+J42+J37+J36 -> 40998
E48: SCOPA | F48: =F37 -> 13580 | G48: =G37 -> 9870 | H48: =H37 -> 11144 | I48: =I37 -> 11698 | J48: =J37 -> 11562
E49: A & G | F49: =F43+F42+F36 -> 15798.5 | G49: =G43+G42+G36 -> 17807.5 | H49: =H43+H42+H36 -> 16310.4 | I49: =I43+I42+I36 -> 16825.1 | J49: =J43+J42+J36 -> 20111.1
E50: Argent perdu | F50: =F44 -> 5621.5 | G50: =G44 -> 7322.5 | H50: =H44 -> 7542.6 | I50: =I44 -> 6475.9 | J50: =J44 -> 9324.9
N52: 238000
G53: SCOPA | H53: 11562 | N53: 100000 | O53: sans TVA | P53: =N53/N52 -> 0.42016807
G54: A & P | H54: 20111 | N54: 138000 | P54: =N54/N52 -> 0.57983193
G55: Argent perdu | H55: 9324
G65: =18*4 -> 72 | H65: 500 | I65: =H65*G65 -> 36000
G66: =G65 -> 72 | H66: 400 | I66: =H66*G66 -> 28800
G67: 16 | H67: 650 | I67: =H67*G67 -> 10400
